{
  "e98a9c294df77ddb": [
    {
      "graph_id_type": "md_id",
      "proprietary_id": "mp-540788",
      "datasource": "MP",
      "url": "https://next-gen.materialsproject.org/materials/mp-540788",
      "filehash": "f4214f5b8319edc8"
    }
  ],
  "f13422bfed1742ba": [
    {
      "graph_id_type": "topo_md_id",
      "proprietary_id": "mp-540788",
      "datasource": "MP",
      "url": "https://next-gen.materialsproject.org/materials/mp-540788",
      "filehash": "f4214f5b8319edc8"
    }
  ],
  "361f1ece886f2afb": [
    {
      "graph_id_type": "dc_id",
      "proprietary_id": "mp-540788",
      "datasource": "MP",
      "url": "https://next-gen.materialsproject.org/materials/mp-540788",
      "filehash": "f4214f5b8319edc8"
    }
  ]
}