{
  "470c996ac404a524": [
    {
      "graph_id_type": "md_id",
      "proprietary_id": "mp-996944",
      "datasource": "MP",
      "url": "https://next-gen.materialsproject.org/materials/mp-996944",
      "filehash": "6585378cf7230ba1d152d0d17368f8d71a75467a0ea51b46c0e3c43c90c801a7"
    }
  ],
  "8ea938c870d61184": [
    {
      "graph_id_type": "topo_md_id",
      "proprietary_id": "mp-996944",
      "datasource": "MP",
      "url": "https://next-gen.materialsproject.org/materials/mp-996944",
      "filehash": "6585378cf7230ba1d152d0d17368f8d71a75467a0ea51b46c0e3c43c90c801a7"
    }
  ],
  "9741ad9231fcd8bc": [
    {
      "graph_id_type": "dc_id",
      "proprietary_id": "mp-996944",
      "datasource": "MP",
      "url": "https://next-gen.materialsproject.org/materials/mp-996944",
      "filehash": "6585378cf7230ba1d152d0d17368f8d71a75467a0ea51b46c0e3c43c90c801a7"
    }
  ]
}