{
  "a34d76ecb08ac8dc": [
    {
      "graph_id_type": "md_id",
      "proprietary_id": "mp-1236546",
      "datasource": "MP",
      "url": "https://next-gen.materialsproject.org/materials/mp-1236546",
      "filehash": "c1db3618e352f4aeb45af08f3007583303b856ae06454e9e8e68037193b4e194"
    }
  ],
  "caae5419fe2e8eae": [
    {
      "graph_id_type": "topo_md_id",
      "proprietary_id": "mp-1236546",
      "datasource": "MP",
      "url": "https://next-gen.materialsproject.org/materials/mp-1236546",
      "filehash": "c1db3618e352f4aeb45af08f3007583303b856ae06454e9e8e68037193b4e194"
    }
  ],
  "cdc7e17817cb3036": [
    {
      "graph_id_type": "dc_id",
      "proprietary_id": "mp-1236546",
      "datasource": "MP",
      "url": "https://next-gen.materialsproject.org/materials/mp-1236546",
      "filehash": "c1db3618e352f4aeb45af08f3007583303b856ae06454e9e8e68037193b4e194"
    }
  ],
  "e66d0502f7505b37": [
    {
      "graph_id_type": "md_id",
      "proprietary_id": "mp-1236487",
      "datasource": "MP",
      "url": "https://next-gen.materialsproject.org/materials/mp-1236487",
      "filehash": "560ddb95ced30870b01fec6bfd5732ceea99e70bdc589c9dd5b195dff88f3c2c"
    }
  ],
  "9475a25cce9ceabc": [
    {
      "graph_id_type": "topo_md_id",
      "proprietary_id": "mp-1236487",
      "datasource": "MP",
      "url": "https://next-gen.materialsproject.org/materials/mp-1236487",
      "filehash": "560ddb95ced30870b01fec6bfd5732ceea99e70bdc589c9dd5b195dff88f3c2c"
    }
  ],
  "e1d6f96012ec6bfe": [
    {
      "graph_id_type": "dc_id",
      "proprietary_id": "mp-1236487",
      "datasource": "MP",
      "url": "https://next-gen.materialsproject.org/materials/mp-1236487",
      "filehash": "560ddb95ced30870b01fec6bfd5732ceea99e70bdc589c9dd5b195dff88f3c2c"
    }
  ],
  "53a363af366c39ad": [
    {
      "graph_id_type": "md_id",
      "proprietary_id": "mp-1235319",
      "datasource": "MP",
      "url": "https://next-gen.materialsproject.org/materials/mp-1235319",
      "filehash": "98d782ac4b8f6cbe6fc75ef9ed13227d167151ebb637aa741a01b90059e474da"
    }
  ],
  "dc958a6d828da04c": [
    {
      "graph_id_type": "topo_md_id",
      "proprietary_id": "mp-1235319",
      "datasource": "MP",
      "url": "https://next-gen.materialsproject.org/materials/mp-1235319",
      "filehash": "98d782ac4b8f6cbe6fc75ef9ed13227d167151ebb637aa741a01b90059e474da"
    }
  ],
  "1c697a5434818edc": [
    {
      "graph_id_type": "dc_id",
      "proprietary_id": "mp-1235319",
      "datasource": "MP",
      "url": "https://next-gen.materialsproject.org/materials/mp-1235319",
      "filehash": "98d782ac4b8f6cbe6fc75ef9ed13227d167151ebb637aa741a01b90059e474da"
    }
  ]
}