{
  "db4fb2f9167b769f": [
    {
      "graph_id_type": "md_id",
      "proprietary_id": "mp-1181036",
      "datasource": "MP",
      "url": "https://next-gen.materialsproject.org/materials/mp-1181036",
      "filehash": "cb0e62263d9357d110653c25f54298c764f0d618e1a277f6b51d6e8624c92ebf"
    }
  ],
  "fc91518e9fa8d23b": [
    {
      "graph_id_type": "topo_md_id",
      "proprietary_id": "mp-1181036",
      "datasource": "MP",
      "url": "https://next-gen.materialsproject.org/materials/mp-1181036",
      "filehash": "cb0e62263d9357d110653c25f54298c764f0d618e1a277f6b51d6e8624c92ebf"
    }
  ],
  "d88b34e47e9ac06d": [
    {
      "graph_id_type": "dc_id",
      "proprietary_id": "mp-1181036",
      "datasource": "MP",
      "url": "https://next-gen.materialsproject.org/materials/mp-1181036",
      "filehash": "cb0e62263d9357d110653c25f54298c764f0d618e1a277f6b51d6e8624c92ebf"
    }
  ]
}