{
  "7970c03c60e1a901": [
    {
      "graph_id_type": "md_id",
      "proprietary_id": "mp-1182031",
      "datasource": "MP",
      "url": "https://next-gen.materialsproject.org/materials/mp-1182031",
      "filehash": "887da973cacf1be2c5e80e51763575b7a8d9114ca5a217f69da2449c02803f2c"
    }
  ],
  "00ee32c96b928fbf": [
    {
      "graph_id_type": "topo_md_id",
      "proprietary_id": "mp-1182031",
      "datasource": "MP",
      "url": "https://next-gen.materialsproject.org/materials/mp-1182031",
      "filehash": "887da973cacf1be2c5e80e51763575b7a8d9114ca5a217f69da2449c02803f2c"
    }
  ],
  "6c496c3ec24ed778": [
    {
      "graph_id_type": "dc_id",
      "proprietary_id": "mp-1182031",
      "datasource": "MP",
      "url": "https://next-gen.materialsproject.org/materials/mp-1182031",
      "filehash": "887da973cacf1be2c5e80e51763575b7a8d9114ca5a217f69da2449c02803f2c"
    }
  ],
  "369b3409b886e2c4": [
    {
      "graph_id_type": "md_id",
      "proprietary_id": "mp-1194156",
      "datasource": "MP",
      "url": "https://next-gen.materialsproject.org/materials/mp-1194156",
      "filehash": "438fbb1dc206386735701c381eca92ddc08371191a0b9391ca7ca33837cf3bf4"
    }
  ],
  "7ee4f96df39ac2b7": [
    {
      "graph_id_type": "topo_md_id",
      "proprietary_id": "mp-1194156",
      "datasource": "MP",
      "url": "https://next-gen.materialsproject.org/materials/mp-1194156",
      "filehash": "438fbb1dc206386735701c381eca92ddc08371191a0b9391ca7ca33837cf3bf4"
    }
  ],
  "f8c8fec2e9f54a6e": [
    {
      "graph_id_type": "dc_id",
      "proprietary_id": "mp-1194156",
      "datasource": "MP",
      "url": "https://next-gen.materialsproject.org/materials/mp-1194156",
      "filehash": "438fbb1dc206386735701c381eca92ddc08371191a0b9391ca7ca33837cf3bf4"
    }
  ],
  "d106298f47ff4118": [
    {
      "graph_id_type": "md_id",
      "proprietary_id": "mp-1192758",
      "datasource": "MP",
      "url": "https://next-gen.materialsproject.org/materials/mp-1192758",
      "filehash": "a37049f4e36e7c05fa3d16278874c1bd195e35b0f3e22fa365d5bb867d12697d"
    }
  ],
  "28e1a777e5522c9c": [
    {
      "graph_id_type": "topo_md_id",
      "proprietary_id": "mp-1192758",
      "datasource": "MP",
      "url": "https://next-gen.materialsproject.org/materials/mp-1192758",
      "filehash": "a37049f4e36e7c05fa3d16278874c1bd195e35b0f3e22fa365d5bb867d12697d"
    }
  ],
  "da6f5695cdaf18dc": [
    {
      "graph_id_type": "dc_id",
      "proprietary_id": "mp-1192758",
      "datasource": "MP",
      "url": "https://next-gen.materialsproject.org/materials/mp-1192758",
      "filehash": "a37049f4e36e7c05fa3d16278874c1bd195e35b0f3e22fa365d5bb867d12697d"
    }
  ],
  "5f2d4cce530a2e6c": [
    {
      "graph_id_type": "md_id",
      "proprietary_id": "mp-1194309",
      "datasource": "MP",
      "url": "https://next-gen.materialsproject.org/materials/mp-1194309",
      "filehash": "526d5199a2bf4541723dc34bf2e6e6704b6d95f758fc8e18d4ed2a7c36f7cc7e"
    }
  ],
  "edc90c3be1a22948": [
    {
      "graph_id_type": "topo_md_id",
      "proprietary_id": "mp-1194309",
      "datasource": "MP",
      "url": "https://next-gen.materialsproject.org/materials/mp-1194309",
      "filehash": "526d5199a2bf4541723dc34bf2e6e6704b6d95f758fc8e18d4ed2a7c36f7cc7e"
    }
  ],
  "873ea8f51fa5e116": [
    {
      "graph_id_type": "dc_id",
      "proprietary_id": "mp-1194309",
      "datasource": "MP",
      "url": "https://next-gen.materialsproject.org/materials/mp-1194309",
      "filehash": "526d5199a2bf4541723dc34bf2e6e6704b6d95f758fc8e18d4ed2a7c36f7cc7e"
    }
  ]
}