{
  "df5b108b0bc8df35": [
    {
      "graph_id_type": "md_id",
      "proprietary_id": "mp-22129",
      "datasource": "MP",
      "url": "https://next-gen.materialsproject.org/materials/mp-22129",
      "filehash": "c3d2d3cf5102ca9b"
    }
  ],
  "299194b9d518da06": [
    {
      "graph_id_type": "topo_md_id",
      "proprietary_id": "mp-22129",
      "datasource": "MP",
      "url": "https://next-gen.materialsproject.org/materials/mp-22129",
      "filehash": "c3d2d3cf5102ca9b"
    }
  ],
  "425a5ddd7f736c1e": [
    {
      "graph_id_type": "dc_id",
      "proprietary_id": "mp-22129",
      "datasource": "MP",
      "url": "https://next-gen.materialsproject.org/materials/mp-22129",
      "filehash": "c3d2d3cf5102ca9b"
    }
  ]
}