{
  "903fa4937a0baa5b": [
    {
      "graph_id_type": "md_id",
      "proprietary_id": "mp-697253",
      "datasource": "MP",
      "url": "https://next-gen.materialsproject.org/materials/mp-697253",
      "filehash": "df7236a564351129d30993576b6924d6706e93cbb980ca7679df8e46897ca804"
    }
  ],
  "9f94bfea07c484bc": [
    {
      "graph_id_type": "topo_md_id",
      "proprietary_id": "mp-697253",
      "datasource": "MP",
      "url": "https://next-gen.materialsproject.org/materials/mp-697253",
      "filehash": "df7236a564351129d30993576b6924d6706e93cbb980ca7679df8e46897ca804"
    }
  ],
  "fb0cde82b7bb4497": [
    {
      "graph_id_type": "dc_id",
      "proprietary_id": "mp-697253",
      "datasource": "MP",
      "url": "https://next-gen.materialsproject.org/materials/mp-697253",
      "filehash": "df7236a564351129d30993576b6924d6706e93cbb980ca7679df8e46897ca804"
    }
  ]
}