{
  "aca2ea5c59e58423": [
    {
      "graph_id_type": "md_id",
      "proprietary_id": "mp-30028",
      "datasource": "MP",
      "url": "https://next-gen.materialsproject.org/materials/mp-30028",
      "filehash": "c1645807b95a905a7a502fbacf8a946b21667df11e88f9debea51c478cb7df76"
    }
  ],
  "962e8329dd8c4176": [
    {
      "graph_id_type": "topo_md_id",
      "proprietary_id": "mp-30028",
      "datasource": "MP",
      "url": "https://next-gen.materialsproject.org/materials/mp-30028",
      "filehash": "c1645807b95a905a7a502fbacf8a946b21667df11e88f9debea51c478cb7df76"
    }
  ],
  "ca83dfeea4c7d92c": [
    {
      "graph_id_type": "dc_id",
      "proprietary_id": "mp-30028",
      "datasource": "MP",
      "url": "https://next-gen.materialsproject.org/materials/mp-30028",
      "filehash": "c1645807b95a905a7a502fbacf8a946b21667df11e88f9debea51c478cb7df76"
    }
  ]
}