{
  "63afa1dcc3e7fb07": [
    {
      "graph_id_type": "md_id",
      "proprietary_id": "mp-1228599",
      "datasource": "MP",
      "url": "https://next-gen.materialsproject.org/materials/mp-1228599",
      "filehash": "813748bcf9c220fff2dead68d8a4aa530ce47b952c1b3da2d6072756e235fce7"
    }
  ],
  "554c796f7ba80136": [
    {
      "graph_id_type": "topo_md_id",
      "proprietary_id": "mp-1228599",
      "datasource": "MP",
      "url": "https://next-gen.materialsproject.org/materials/mp-1228599",
      "filehash": "813748bcf9c220fff2dead68d8a4aa530ce47b952c1b3da2d6072756e235fce7"
    }
  ],
  "b7edd86b9e310cea": [
    {
      "graph_id_type": "dc_id",
      "proprietary_id": "mp-1228599",
      "datasource": "MP",
      "url": "https://next-gen.materialsproject.org/materials/mp-1228599",
      "filehash": "813748bcf9c220fff2dead68d8a4aa530ce47b952c1b3da2d6072756e235fce7"
    }
  ]
}