{
  "eebb189d5ae4d7c2": [
    {
      "graph_id_type": "md_id",
      "proprietary_id": "mp-1189312",
      "datasource": "MP",
      "url": "https://next-gen.materialsproject.org/materials/mp-1189312",
      "filehash": "9a3ee0ec0ae3e40bd1a4d7198b5e428a9fb32ff5685361c4728e5ed6af8422a2"
    }
  ],
  "024dfda22073912d": [
    {
      "graph_id_type": "topo_md_id",
      "proprietary_id": "mp-1189312",
      "datasource": "MP",
      "url": "https://next-gen.materialsproject.org/materials/mp-1189312",
      "filehash": "9a3ee0ec0ae3e40bd1a4d7198b5e428a9fb32ff5685361c4728e5ed6af8422a2"
    }
  ],
  "11f3ae42f36e54ee": [
    {
      "graph_id_type": "dc_id",
      "proprietary_id": "mp-1189312",
      "datasource": "MP",
      "url": "https://next-gen.materialsproject.org/materials/mp-1189312",
      "filehash": "9a3ee0ec0ae3e40bd1a4d7198b5e428a9fb32ff5685361c4728e5ed6af8422a2"
    }
  ],
  "ce3232e2ee8d2fd5": [
    {
      "graph_id_type": "md_id",
      "proprietary_id": "mp-1238027",
      "datasource": "MP",
      "url": "https://next-gen.materialsproject.org/materials/mp-1238027",
      "filehash": "9d739817671d3953f1e2dc4e406f3e45329d1bf59df6e622b0e4b21406938833"
    }
  ],
  "600144d530d52333": [
    {
      "graph_id_type": "topo_md_id",
      "proprietary_id": "mp-1238027",
      "datasource": "MP",
      "url": "https://next-gen.materialsproject.org/materials/mp-1238027",
      "filehash": "9d739817671d3953f1e2dc4e406f3e45329d1bf59df6e622b0e4b21406938833"
    }
  ],
  "88f7df2664632128": [
    {
      "graph_id_type": "dc_id",
      "proprietary_id": "mp-1238027",
      "datasource": "MP",
      "url": "https://next-gen.materialsproject.org/materials/mp-1238027",
      "filehash": "9d739817671d3953f1e2dc4e406f3e45329d1bf59df6e622b0e4b21406938833"
    }
  ]
}