{
  "724f6bccb8787ec5": [
    {
      "graph_id_type": "md_id",
      "proprietary_id": "mp-757599",
      "datasource": "MP",
      "url": "https://next-gen.materialsproject.org/materials/mp-757599",
      "filehash": "ec0e91cd09024d454b3f83885f222b17319c8c44a934cd53a83b9c6ae86cf610"
    }
  ],
  "82eb76cfbe73b405": [
    {
      "graph_id_type": "topo_md_id",
      "proprietary_id": "mp-757599",
      "datasource": "MP",
      "url": "https://next-gen.materialsproject.org/materials/mp-757599",
      "filehash": "ec0e91cd09024d454b3f83885f222b17319c8c44a934cd53a83b9c6ae86cf610"
    }
  ],
  "baba6a602a11ef71": [
    {
      "graph_id_type": "dc_id",
      "proprietary_id": "mp-757599",
      "datasource": "MP",
      "url": "https://next-gen.materialsproject.org/materials/mp-757599",
      "filehash": "ec0e91cd09024d454b3f83885f222b17319c8c44a934cd53a83b9c6ae86cf610"
    }
  ]
}