{
  "fb6c2b06eb7005ef": [
    {
      "graph_id_type": "md_id",
      "proprietary_id": "mp-1176929",
      "datasource": "MP",
      "url": "https://next-gen.materialsproject.org/materials/mp-1176929",
      "filehash": "e6797528200c1eb6"
    }
  ],
  "4e575dc3f4375626": [
    {
      "graph_id_type": "topo_md_id",
      "proprietary_id": "mp-1176929",
      "datasource": "MP",
      "url": "https://next-gen.materialsproject.org/materials/mp-1176929",
      "filehash": "e6797528200c1eb6"
    }
  ],
  "e7290c2bb954fb69": [
    {
      "graph_id_type": "dc_id",
      "proprietary_id": "mp-1176929",
      "datasource": "MP",
      "url": "https://next-gen.materialsproject.org/materials/mp-1176929",
      "filehash": "e6797528200c1eb6"
    }
  ],
  "910f91d647a213a8": [
    {
      "graph_id_type": "md_id",
      "proprietary_id": "mp-1176922",
      "datasource": "MP",
      "url": "https://next-gen.materialsproject.org/materials/mp-1176922",
      "filehash": "cf0742ef20402618"
    }
  ],
  "20fb64f13fdee851": [
    {
      "graph_id_type": "topo_md_id",
      "proprietary_id": "mp-1176922",
      "datasource": "MP",
      "url": "https://next-gen.materialsproject.org/materials/mp-1176922",
      "filehash": "cf0742ef20402618"
    }
  ],
  "19e382e8fdd62ca1": [
    {
      "graph_id_type": "dc_id",
      "proprietary_id": "mp-1176922",
      "datasource": "MP",
      "url": "https://next-gen.materialsproject.org/materials/mp-1176922",
      "filehash": "cf0742ef20402618"
    }
  ],
  "079a1d39ee3da082": [
    {
      "graph_id_type": "md_id",
      "proprietary_id": "mp-1176927",
      "datasource": "MP",
      "url": "https://next-gen.materialsproject.org/materials/mp-1176927",
      "filehash": "8fa1875de88f3a2a"
    }
  ],
  "f76ba9786bb4f67e": [
    {
      "graph_id_type": "topo_md_id",
      "proprietary_id": "mp-1176927",
      "datasource": "MP",
      "url": "https://next-gen.materialsproject.org/materials/mp-1176927",
      "filehash": "8fa1875de88f3a2a"
    }
  ],
  "8454893774c3e9b2": [
    {
      "graph_id_type": "dc_id",
      "proprietary_id": "mp-1176927",
      "datasource": "MP",
      "url": "https://next-gen.materialsproject.org/materials/mp-1176927",
      "filehash": "8fa1875de88f3a2a"
    }
  ],
  "1d2117f5d032e884": [
    {
      "graph_id_type": "md_id",
      "proprietary_id": "mp-1176908",
      "datasource": "MP",
      "url": "https://next-gen.materialsproject.org/materials/mp-1176908",
      "filehash": "9ed66352990b6724"
    },
    {
      "graph_id_type": "md_id",
      "proprietary_id": "mp-773693",
      "datasource": "MP",
      "url": "https://next-gen.materialsproject.org/materials/mp-773693",
      "filehash": "fb3f2661fe89c0f1"
    }
  ],
  "dbbe128263257b8d": [
    {
      "graph_id_type": "topo_md_id",
      "proprietary_id": "mp-1176908",
      "datasource": "MP",
      "url": "https://next-gen.materialsproject.org/materials/mp-1176908",
      "filehash": "9ed66352990b6724"
    },
    {
      "graph_id_type": "topo_md_id",
      "proprietary_id": "mp-773693",
      "datasource": "MP",
      "url": "https://next-gen.materialsproject.org/materials/mp-773693",
      "filehash": "fb3f2661fe89c0f1"
    }
  ],
  "1233794b565eb776": [
    {
      "graph_id_type": "dc_id",
      "proprietary_id": "mp-1176908",
      "datasource": "MP",
      "url": "https://next-gen.materialsproject.org/materials/mp-1176908",
      "filehash": "9ed66352990b6724"
    }
  ],
  "06da973719b78dfb": [
    {
      "graph_id_type": "md_id",
      "proprietary_id": "mp-1176944",
      "datasource": "MP",
      "url": "https://next-gen.materialsproject.org/materials/mp-1176944",
      "filehash": "aed5b131a270e0c3"
    }
  ],
  "01282655146e149e": [
    {
      "graph_id_type": "topo_md_id",
      "proprietary_id": "mp-1176944",
      "datasource": "MP",
      "url": "https://next-gen.materialsproject.org/materials/mp-1176944",
      "filehash": "aed5b131a270e0c3"
    }
  ],
  "94183f32c1d7b5e5": [
    {
      "graph_id_type": "dc_id",
      "proprietary_id": "mp-1176944",
      "datasource": "MP",
      "url": "https://next-gen.materialsproject.org/materials/mp-1176944",
      "filehash": "aed5b131a270e0c3"
    }
  ],
  "fb8fd81649328830": [
    {
      "graph_id_type": "md_id",
      "proprietary_id": "mp-1176923",
      "datasource": "MP",
      "url": "https://next-gen.materialsproject.org/materials/mp-1176923",
      "filehash": "3261f0c0025d14e7"
    }
  ],
  "bdd14a1ca84e6bdd": [
    {
      "graph_id_type": "topo_md_id",
      "proprietary_id": "mp-1176923",
      "datasource": "MP",
      "url": "https://next-gen.materialsproject.org/materials/mp-1176923",
      "filehash": "3261f0c0025d14e7"
    }
  ],
  "5134fdcbc9737a2f": [
    {
      "graph_id_type": "dc_id",
      "proprietary_id": "mp-1176923",
      "datasource": "MP",
      "url": "https://next-gen.materialsproject.org/materials/mp-1176923",
      "filehash": "3261f0c0025d14e7"
    }
  ],
  "4712cddaa9b9455b": [
    {
      "graph_id_type": "md_id",
      "proprietary_id": "mp-1176918",
      "datasource": "MP",
      "url": "https://next-gen.materialsproject.org/materials/mp-1176918",
      "filehash": "4c4b880ae12b4734"
    }
  ],
  "2128995b50287b68": [
    {
      "graph_id_type": "topo_md_id",
      "proprietary_id": "mp-1176918",
      "datasource": "MP",
      "url": "https://next-gen.materialsproject.org/materials/mp-1176918",
      "filehash": "4c4b880ae12b4734"
    }
  ],
  "ee4e319e293fec28": [
    {
      "graph_id_type": "dc_id",
      "proprietary_id": "mp-1176918",
      "datasource": "MP",
      "url": "https://next-gen.materialsproject.org/materials/mp-1176918",
      "filehash": "4c4b880ae12b4734"
    }
  ],
  "628cbd6e88f16903": [
    {
      "graph_id_type": "md_id",
      "proprietary_id": "mp-1176916",
      "datasource": "MP",
      "url": "https://next-gen.materialsproject.org/materials/mp-1176916",
      "filehash": "b10ebd76e65197bf"
    }
  ],
  "7effa98452b2ce4a": [
    {
      "graph_id_type": "topo_md_id",
      "proprietary_id": "mp-1176916",
      "datasource": "MP",
      "url": "https://next-gen.materialsproject.org/materials/mp-1176916",
      "filehash": "b10ebd76e65197bf"
    }
  ],
  "342b4818f3516b9c": [
    {
      "graph_id_type": "dc_id",
      "proprietary_id": "mp-1176916",
      "datasource": "MP",
      "url": "https://next-gen.materialsproject.org/materials/mp-1176916",
      "filehash": "b10ebd76e65197bf"
    }
  ],
  "510895abb03b4539": [
    {
      "graph_id_type": "md_id",
      "proprietary_id": "mp-1176930",
      "datasource": "MP",
      "url": "https://next-gen.materialsproject.org/materials/mp-1176930",
      "filehash": "54a24d8d95c41dd3"
    }
  ],
  "8d23166caad49911": [
    {
      "graph_id_type": "topo_md_id",
      "proprietary_id": "mp-1176930",
      "datasource": "MP",
      "url": "https://next-gen.materialsproject.org/materials/mp-1176930",
      "filehash": "54a24d8d95c41dd3"
    }
  ],
  "b4b89d4a0abba024": [
    {
      "graph_id_type": "dc_id",
      "proprietary_id": "mp-1176930",
      "datasource": "MP",
      "url": "https://next-gen.materialsproject.org/materials/mp-1176930",
      "filehash": "54a24d8d95c41dd3"
    }
  ],
  "ddd1cc9f88175507": [
    {
      "graph_id_type": "md_id",
      "proprietary_id": "mp-1177041",
      "datasource": "MP",
      "url": "https://next-gen.materialsproject.org/materials/mp-1177041",
      "filehash": "01565838a1fdc9d5"
    }
  ],
  "eb4dd408f05f9478": [
    {
      "graph_id_type": "topo_md_id",
      "proprietary_id": "mp-1177041",
      "datasource": "MP",
      "url": "https://next-gen.materialsproject.org/materials/mp-1177041",
      "filehash": "01565838a1fdc9d5"
    }
  ],
  "4d1ac521693cddbe": [
    {
      "graph_id_type": "dc_id",
      "proprietary_id": "mp-1177041",
      "datasource": "MP",
      "url": "https://next-gen.materialsproject.org/materials/mp-1177041",
      "filehash": "01565838a1fdc9d5"
    }
  ],
  "cb76a7a7c58de105": [
    {
      "graph_id_type": "md_id",
      "proprietary_id": "mp-1177009",
      "datasource": "MP",
      "url": "https://next-gen.materialsproject.org/materials/mp-1177009",
      "filehash": "9c8d3b8ac83dc312"
    }
  ],
  "391a6ca686874910": [
    {
      "graph_id_type": "topo_md_id",
      "proprietary_id": "mp-1177009",
      "datasource": "MP",
      "url": "https://next-gen.materialsproject.org/materials/mp-1177009",
      "filehash": "9c8d3b8ac83dc312"
    }
  ],
  "77f2385e06f2fd5f": [
    {
      "graph_id_type": "dc_id",
      "proprietary_id": "mp-1177009",
      "datasource": "MP",
      "url": "https://next-gen.materialsproject.org/materials/mp-1177009",
      "filehash": "9c8d3b8ac83dc312"
    }
  ],
  "a29f76ae5baf7186": [
    {
      "graph_id_type": "md_id",
      "proprietary_id": "mp-1176948",
      "datasource": "MP",
      "url": "https://next-gen.materialsproject.org/materials/mp-1176948",
      "filehash": "8b836020504c3640"
    }
  ],
  "34f8ce6526251dbe": [
    {
      "graph_id_type": "topo_md_id",
      "proprietary_id": "mp-1176948",
      "datasource": "MP",
      "url": "https://next-gen.materialsproject.org/materials/mp-1176948",
      "filehash": "8b836020504c3640"
    }
  ],
  "9de39841fdcb94d4": [
    {
      "graph_id_type": "dc_id",
      "proprietary_id": "mp-1176948",
      "datasource": "MP",
      "url": "https://next-gen.materialsproject.org/materials/mp-1176948",
      "filehash": "8b836020504c3640"
    }
  ],
  "54ebe4d41af5c775": [
    {
      "graph_id_type": "md_id",
      "proprietary_id": "mp-1176917",
      "datasource": "MP",
      "url": "https://next-gen.materialsproject.org/materials/mp-1176917",
      "filehash": "0a1fbdcc1792bd6f"
    }
  ],
  "78ec03e58480b357": [
    {
      "graph_id_type": "topo_md_id",
      "proprietary_id": "mp-1176917",
      "datasource": "MP",
      "url": "https://next-gen.materialsproject.org/materials/mp-1176917",
      "filehash": "0a1fbdcc1792bd6f"
    }
  ],
  "b6fe0381e72a5aaf": [
    {
      "graph_id_type": "dc_id",
      "proprietary_id": "mp-1176917",
      "datasource": "MP",
      "url": "https://next-gen.materialsproject.org/materials/mp-1176917",
      "filehash": "0a1fbdcc1792bd6f"
    }
  ],
  "06d29816a398be2d": [
    {
      "graph_id_type": "md_id",
      "proprietary_id": "mp-1176942",
      "datasource": "MP",
      "url": "https://next-gen.materialsproject.org/materials/mp-1176942",
      "filehash": "727925e7c248822a"
    }
  ],
  "0a0f13d0e11b5f22": [
    {
      "graph_id_type": "topo_md_id",
      "proprietary_id": "mp-1176942",
      "datasource": "MP",
      "url": "https://next-gen.materialsproject.org/materials/mp-1176942",
      "filehash": "727925e7c248822a"
    }
  ],
  "af3879b923fe94e1": [
    {
      "graph_id_type": "dc_id",
      "proprietary_id": "mp-1176942",
      "datasource": "MP",
      "url": "https://next-gen.materialsproject.org/materials/mp-1176942",
      "filehash": "727925e7c248822a"
    }
  ],
  "2f9a82a1fac4f744": [
    {
      "graph_id_type": "md_id",
      "proprietary_id": "mp-1176920",
      "datasource": "MP",
      "url": "https://next-gen.materialsproject.org/materials/mp-1176920",
      "filehash": "17b3df98b9a0a70c"
    }
  ],
  "d845f9c9d86ea297": [
    {
      "graph_id_type": "topo_md_id",
      "proprietary_id": "mp-1176920",
      "datasource": "MP",
      "url": "https://next-gen.materialsproject.org/materials/mp-1176920",
      "filehash": "17b3df98b9a0a70c"
    }
  ],
  "e1ec424aee3c15f3": [
    {
      "graph_id_type": "dc_id",
      "proprietary_id": "mp-1176920",
      "datasource": "MP",
      "url": "https://next-gen.materialsproject.org/materials/mp-1176920",
      "filehash": "17b3df98b9a0a70c"
    }
  ],
  "3b6ca9feff216613": [
    {
      "graph_id_type": "md_id",
      "proprietary_id": "mp-1176921",
      "datasource": "MP",
      "url": "https://next-gen.materialsproject.org/materials/mp-1176921",
      "filehash": "b33754b0e86a7515"
    }
  ],
  "38437153cb19bd2e": [
    {
      "graph_id_type": "topo_md_id",
      "proprietary_id": "mp-1176921",
      "datasource": "MP",
      "url": "https://next-gen.materialsproject.org/materials/mp-1176921",
      "filehash": "b33754b0e86a7515"
    }
  ],
  "a26019b8905b02c5": [
    {
      "graph_id_type": "dc_id",
      "proprietary_id": "mp-1176921",
      "datasource": "MP",
      "url": "https://next-gen.materialsproject.org/materials/mp-1176921",
      "filehash": "b33754b0e86a7515"
    }
  ],
  "14e5aad76eadeda3": [
    {
      "graph_id_type": "md_id",
      "proprietary_id": "mp-1177106",
      "datasource": "MP",
      "url": "https://next-gen.materialsproject.org/materials/mp-1177106",
      "filehash": "42bd7e4ae0af093c"
    }
  ],
  "66bfce4590858c66": [
    {
      "graph_id_type": "topo_md_id",
      "proprietary_id": "mp-1177106",
      "datasource": "MP",
      "url": "https://next-gen.materialsproject.org/materials/mp-1177106",
      "filehash": "42bd7e4ae0af093c"
    }
  ],
  "8bfd325f63769011": [
    {
      "graph_id_type": "dc_id",
      "proprietary_id": "mp-1177106",
      "datasource": "MP",
      "url": "https://next-gen.materialsproject.org/materials/mp-1177106",
      "filehash": "42bd7e4ae0af093c"
    }
  ],
  "dcea90362438e85d": [
    {
      "graph_id_type": "md_id",
      "proprietary_id": "mp-1176919",
      "datasource": "MP",
      "url": "https://next-gen.materialsproject.org/materials/mp-1176919",
      "filehash": "8b792bf36b79147f"
    }
  ],
  "090342f5bd21f773": [
    {
      "graph_id_type": "topo_md_id",
      "proprietary_id": "mp-1176919",
      "datasource": "MP",
      "url": "https://next-gen.materialsproject.org/materials/mp-1176919",
      "filehash": "8b792bf36b79147f"
    }
  ],
  "2bcb00690e60b5c5": [
    {
      "graph_id_type": "dc_id",
      "proprietary_id": "mp-1176919",
      "datasource": "MP",
      "url": "https://next-gen.materialsproject.org/materials/mp-1176919",
      "filehash": "8b792bf36b79147f"
    }
  ],
  "bc451e245a7f5e1e": [
    {
      "graph_id_type": "md_id",
      "proprietary_id": "mp-1176943",
      "datasource": "MP",
      "url": "https://next-gen.materialsproject.org/materials/mp-1176943",
      "filehash": "cfaf63dbe8a280d2"
    }
  ],
  "2c4f84d0cd253e81": [
    {
      "graph_id_type": "topo_md_id",
      "proprietary_id": "mp-1176943",
      "datasource": "MP",
      "url": "https://next-gen.materialsproject.org/materials/mp-1176943",
      "filehash": "cfaf63dbe8a280d2"
    }
  ],
  "6b0ec47db55bcd00": [
    {
      "graph_id_type": "dc_id",
      "proprietary_id": "mp-1176943",
      "datasource": "MP",
      "url": "https://next-gen.materialsproject.org/materials/mp-1176943",
      "filehash": "cfaf63dbe8a280d2"
    }
  ],
  "65d5005af0325083": [
    {
      "graph_id_type": "md_id",
      "proprietary_id": "mp-1176915",
      "datasource": "MP",
      "url": "https://next-gen.materialsproject.org/materials/mp-1176915",
      "filehash": "bd1aef4ed47cece9"
    }
  ],
  "48cfe9326eeb670a": [
    {
      "graph_id_type": "topo_md_id",
      "proprietary_id": "mp-1176915",
      "datasource": "MP",
      "url": "https://next-gen.materialsproject.org/materials/mp-1176915",
      "filehash": "bd1aef4ed47cece9"
    }
  ],
  "4cf2aaca10133609": [
    {
      "graph_id_type": "dc_id",
      "proprietary_id": "mp-1176915",
      "datasource": "MP",
      "url": "https://next-gen.materialsproject.org/materials/mp-1176915",
      "filehash": "bd1aef4ed47cece9"
    }
  ],
  "9d833f7f2a0ae77f": [
    {
      "graph_id_type": "md_id",
      "proprietary_id": "mp-1176932",
      "datasource": "MP",
      "url": "https://next-gen.materialsproject.org/materials/mp-1176932",
      "filehash": "6a0a7a007a8a41cf"
    }
  ],
  "a09404837abd790c": [
    {
      "graph_id_type": "topo_md_id",
      "proprietary_id": "mp-1176932",
      "datasource": "MP",
      "url": "https://next-gen.materialsproject.org/materials/mp-1176932",
      "filehash": "6a0a7a007a8a41cf"
    }
  ],
  "13459e139ab9719c": [
    {
      "graph_id_type": "dc_id",
      "proprietary_id": "mp-1176932",
      "datasource": "MP",
      "url": "https://next-gen.materialsproject.org/materials/mp-1176932",
      "filehash": "6a0a7a007a8a41cf"
    }
  ],
  "a5cf5e06a0cd48cb": [
    {
      "graph_id_type": "md_id",
      "proprietary_id": "mp-1176914",
      "datasource": "MP",
      "url": "https://next-gen.materialsproject.org/materials/mp-1176914",
      "filehash": "a5c7a592c7d65354"
    }
  ],
  "d4595bc69f57c232": [
    {
      "graph_id_type": "topo_md_id",
      "proprietary_id": "mp-1176914",
      "datasource": "MP",
      "url": "https://next-gen.materialsproject.org/materials/mp-1176914",
      "filehash": "a5c7a592c7d65354"
    }
  ],
  "7203442e1ec8bbfa": [
    {
      "graph_id_type": "dc_id",
      "proprietary_id": "mp-1176914",
      "datasource": "MP",
      "url": "https://next-gen.materialsproject.org/materials/mp-1176914",
      "filehash": "a5c7a592c7d65354"
    }
  ],
  "217631dc6d20f8af": [
    {
      "graph_id_type": "md_id",
      "proprietary_id": "mp-1176925",
      "datasource": "MP",
      "url": "https://next-gen.materialsproject.org/materials/mp-1176925",
      "filehash": "4d2a39b987aed046"
    }
  ],
  "11eb9be7e4f9210e": [
    {
      "graph_id_type": "topo_md_id",
      "proprietary_id": "mp-1176925",
      "datasource": "MP",
      "url": "https://next-gen.materialsproject.org/materials/mp-1176925",
      "filehash": "4d2a39b987aed046"
    }
  ],
  "ef23a7f64a3b5357": [
    {
      "graph_id_type": "dc_id",
      "proprietary_id": "mp-1176925",
      "datasource": "MP",
      "url": "https://next-gen.materialsproject.org/materials/mp-1176925",
      "filehash": "4d2a39b987aed046"
    }
  ],
  "659312228d9e9d88": [
    {
      "graph_id_type": "md_id",
      "proprietary_id": "mp-1176926",
      "datasource": "MP",
      "url": "https://next-gen.materialsproject.org/materials/mp-1176926",
      "filehash": "7aad088a15141395"
    }
  ],
  "7145c1a9efbc9eaa": [
    {
      "graph_id_type": "topo_md_id",
      "proprietary_id": "mp-1176926",
      "datasource": "MP",
      "url": "https://next-gen.materialsproject.org/materials/mp-1176926",
      "filehash": "7aad088a15141395"
    }
  ],
  "4e5064ed177db364": [
    {
      "graph_id_type": "dc_id",
      "proprietary_id": "mp-1176926",
      "datasource": "MP",
      "url": "https://next-gen.materialsproject.org/materials/mp-1176926",
      "filehash": "7aad088a15141395"
    }
  ],
  "2346a79a0f650b9c": [
    {
      "graph_id_type": "md_id",
      "proprietary_id": "mp-1176928",
      "datasource": "MP",
      "url": "https://next-gen.materialsproject.org/materials/mp-1176928",
      "filehash": "f6847b86b6e9bbca"
    }
  ],
  "833f9b1ad95c3488": [
    {
      "graph_id_type": "topo_md_id",
      "proprietary_id": "mp-1176928",
      "datasource": "MP",
      "url": "https://next-gen.materialsproject.org/materials/mp-1176928",
      "filehash": "f6847b86b6e9bbca"
    }
  ],
  "3561767ac414ce7a": [
    {
      "graph_id_type": "dc_id",
      "proprietary_id": "mp-1176928",
      "datasource": "MP",
      "url": "https://next-gen.materialsproject.org/materials/mp-1176928",
      "filehash": "f6847b86b6e9bbca"
    }
  ],
  "e6b344e0ff1ba796": [
    {
      "graph_id_type": "md_id",
      "proprietary_id": "mp-1177068",
      "datasource": "MP",
      "url": "https://next-gen.materialsproject.org/materials/mp-1177068",
      "filehash": "203b9ea9fbd9306f"
    }
  ],
  "3b7608cdd40f43b6": [
    {
      "graph_id_type": "topo_md_id",
      "proprietary_id": "mp-1177068",
      "datasource": "MP",
      "url": "https://next-gen.materialsproject.org/materials/mp-1177068",
      "filehash": "203b9ea9fbd9306f"
    }
  ],
  "9670791a681ef2c7": [
    {
      "graph_id_type": "dc_id",
      "proprietary_id": "mp-1177068",
      "datasource": "MP",
      "url": "https://next-gen.materialsproject.org/materials/mp-1177068",
      "filehash": "203b9ea9fbd9306f"
    }
  ],
  "c7f7be4993354826": [
    {
      "graph_id_type": "md_id",
      "proprietary_id": "mp-1176912",
      "datasource": "MP",
      "url": "https://next-gen.materialsproject.org/materials/mp-1176912",
      "filehash": "1129db44334802b3"
    }
  ],
  "5f81dbe6a44979b3": [
    {
      "graph_id_type": "topo_md_id",
      "proprietary_id": "mp-1176912",
      "datasource": "MP",
      "url": "https://next-gen.materialsproject.org/materials/mp-1176912",
      "filehash": "1129db44334802b3"
    }
  ],
  "48cbabd423ade6f3": [
    {
      "graph_id_type": "dc_id",
      "proprietary_id": "mp-1176912",
      "datasource": "MP",
      "url": "https://next-gen.materialsproject.org/materials/mp-1176912",
      "filehash": "1129db44334802b3"
    }
  ],
  "255e70ce64c830c2": [
    {
      "graph_id_type": "md_id",
      "proprietary_id": "mp-1177100",
      "datasource": "MP",
      "url": "https://next-gen.materialsproject.org/materials/mp-1177100",
      "filehash": "8e05186336086a9f"
    }
  ],
  "f1f04336787a39fc": [
    {
      "graph_id_type": "topo_md_id",
      "proprietary_id": "mp-1177100",
      "datasource": "MP",
      "url": "https://next-gen.materialsproject.org/materials/mp-1177100",
      "filehash": "8e05186336086a9f"
    }
  ],
  "848b673ae5762e14": [
    {
      "graph_id_type": "dc_id",
      "proprietary_id": "mp-1177100",
      "datasource": "MP",
      "url": "https://next-gen.materialsproject.org/materials/mp-1177100",
      "filehash": "8e05186336086a9f"
    }
  ],
  "5bef301755fcd061": [
    {
      "graph_id_type": "md_id",
      "proprietary_id": "mp-1177111",
      "datasource": "MP",
      "url": "https://next-gen.materialsproject.org/materials/mp-1177111",
      "filehash": "b69c4e653f7248bc"
    }
  ],
  "897cc26ef06bd7bf": [
    {
      "graph_id_type": "topo_md_id",
      "proprietary_id": "mp-1177111",
      "datasource": "MP",
      "url": "https://next-gen.materialsproject.org/materials/mp-1177111",
      "filehash": "b69c4e653f7248bc"
    }
  ],
  "c94336a1b29e4b2a": [
    {
      "graph_id_type": "dc_id",
      "proprietary_id": "mp-1177111",
      "datasource": "MP",
      "url": "https://next-gen.materialsproject.org/materials/mp-1177111",
      "filehash": "b69c4e653f7248bc"
    }
  ],
  "5af57180b0395a98": [
    {
      "graph_id_type": "md_id",
      "proprietary_id": "mp-1176935",
      "datasource": "MP",
      "url": "https://next-gen.materialsproject.org/materials/mp-1176935",
      "filehash": "a644f972b63dc7bb"
    }
  ],
  "c42d2727bf4f3751": [
    {
      "graph_id_type": "topo_md_id",
      "proprietary_id": "mp-1176935",
      "datasource": "MP",
      "url": "https://next-gen.materialsproject.org/materials/mp-1176935",
      "filehash": "a644f972b63dc7bb"
    }
  ],
  "fe435e02844c31e6": [
    {
      "graph_id_type": "dc_id",
      "proprietary_id": "mp-1176935",
      "datasource": "MP",
      "url": "https://next-gen.materialsproject.org/materials/mp-1176935",
      "filehash": "a644f972b63dc7bb"
    }
  ],
  "521e0fe4ec5b3f7e": [
    {
      "graph_id_type": "md_id",
      "proprietary_id": "mp-1176938",
      "datasource": "MP",
      "url": "https://next-gen.materialsproject.org/materials/mp-1176938",
      "filehash": "df4dbf177d95e43c"
    }
  ],
  "8bda96c526baba65": [
    {
      "graph_id_type": "topo_md_id",
      "proprietary_id": "mp-1176938",
      "datasource": "MP",
      "url": "https://next-gen.materialsproject.org/materials/mp-1176938",
      "filehash": "df4dbf177d95e43c"
    }
  ],
  "2d891b76f4ff19f0": [
    {
      "graph_id_type": "dc_id",
      "proprietary_id": "mp-1176938",
      "datasource": "MP",
      "url": "https://next-gen.materialsproject.org/materials/mp-1176938",
      "filehash": "df4dbf177d95e43c"
    }
  ],
  "1f11f979260c0a92": [
    {
      "graph_id_type": "dc_id",
      "proprietary_id": "mp-773693",
      "datasource": "MP",
      "url": "https://next-gen.materialsproject.org/materials/mp-773693",
      "filehash": "fb3f2661fe89c0f1"
    }
  ],
  "b5723ba5fdca310c": [
    {
      "graph_id_type": "md_id",
      "proprietary_id": "mp-774273",
      "datasource": "MP",
      "url": "https://next-gen.materialsproject.org/materials/mp-774273",
      "filehash": "a766d6d3ddbbd18c"
    }
  ],
  "3c8aa9b0db824f41": [
    {
      "graph_id_type": "topo_md_id",
      "proprietary_id": "mp-774273",
      "datasource": "MP",
      "url": "https://next-gen.materialsproject.org/materials/mp-774273",
      "filehash": "a766d6d3ddbbd18c"
    }
  ],
  "4eb7f3cd2b0abd99": [
    {
      "graph_id_type": "dc_id",
      "proprietary_id": "mp-774273",
      "datasource": "MP",
      "url": "https://next-gen.materialsproject.org/materials/mp-774273",
      "filehash": "a766d6d3ddbbd18c"
    }
  ],
  "62bd5bdd7c760662": [
    {
      "graph_id_type": "md_id",
      "proprietary_id": "mp-772709",
      "datasource": "MP",
      "url": "https://next-gen.materialsproject.org/materials/mp-772709",
      "filehash": "ab9ad59ea1dc6348"
    }
  ],
  "0c21cb810f49aab5": [
    {
      "graph_id_type": "topo_md_id",
      "proprietary_id": "mp-772709",
      "datasource": "MP",
      "url": "https://next-gen.materialsproject.org/materials/mp-772709",
      "filehash": "ab9ad59ea1dc6348"
    }
  ],
  "7d1bbcbb0291ad2b": [
    {
      "graph_id_type": "dc_id",
      "proprietary_id": "mp-772709",
      "datasource": "MP",
      "url": "https://next-gen.materialsproject.org/materials/mp-772709",
      "filehash": "ab9ad59ea1dc6348"
    }
  ],
  "f8a5b8786eb12628": [
    {
      "graph_id_type": "md_id",
      "proprietary_id": "mp-772985",
      "datasource": "MP",
      "url": "https://next-gen.materialsproject.org/materials/mp-772985",
      "filehash": "d01a443bd87bc60b"
    }
  ],
  "2788d20b00ecf747": [
    {
      "graph_id_type": "topo_md_id",
      "proprietary_id": "mp-772985",
      "datasource": "MP",
      "url": "https://next-gen.materialsproject.org/materials/mp-772985",
      "filehash": "d01a443bd87bc60b"
    }
  ],
  "619001872047ad41": [
    {
      "graph_id_type": "dc_id",
      "proprietary_id": "mp-772985",
      "datasource": "MP",
      "url": "https://next-gen.materialsproject.org/materials/mp-772985",
      "filehash": "d01a443bd87bc60b"
    }
  ],
  "7c6d489ea47feb22": [
    {
      "graph_id_type": "md_id",
      "proprietary_id": "mp-772963",
      "datasource": "MP",
      "url": "https://next-gen.materialsproject.org/materials/mp-772963",
      "filehash": "4a62f3cd170934d0"
    }
  ],
  "70d36d2f78595ef9": [
    {
      "graph_id_type": "topo_md_id",
      "proprietary_id": "mp-772963",
      "datasource": "MP",
      "url": "https://next-gen.materialsproject.org/materials/mp-772963",
      "filehash": "4a62f3cd170934d0"
    }
  ],
  "1d2567a0656fe225": [
    {
      "graph_id_type": "dc_id",
      "proprietary_id": "mp-772963",
      "datasource": "MP",
      "url": "https://next-gen.materialsproject.org/materials/mp-772963",
      "filehash": "4a62f3cd170934d0"
    }
  ],
  "97fa7e755d9c9902": [
    {
      "graph_id_type": "md_id",
      "proprietary_id": "mp-772961",
      "datasource": "MP",
      "url": "https://next-gen.materialsproject.org/materials/mp-772961",
      "filehash": "bf3d8f6f44337a75"
    }
  ],
  "f8d203fe81870cd8": [
    {
      "graph_id_type": "topo_md_id",
      "proprietary_id": "mp-772961",
      "datasource": "MP",
      "url": "https://next-gen.materialsproject.org/materials/mp-772961",
      "filehash": "bf3d8f6f44337a75"
    }
  ],
  "5e169effc0b8c7b4": [
    {
      "graph_id_type": "dc_id",
      "proprietary_id": "mp-772961",
      "datasource": "MP",
      "url": "https://next-gen.materialsproject.org/materials/mp-772961",
      "filehash": "bf3d8f6f44337a75"
    }
  ],
  "246b172a92c1413c": [
    {
      "graph_id_type": "md_id",
      "proprietary_id": "mp-760124",
      "datasource": "MP",
      "url": "https://next-gen.materialsproject.org/materials/mp-760124",
      "filehash": "92b983078f329a96"
    }
  ],
  "4f761828d1fcc8cf": [
    {
      "graph_id_type": "topo_md_id",
      "proprietary_id": "mp-760124",
      "datasource": "MP",
      "url": "https://next-gen.materialsproject.org/materials/mp-760124",
      "filehash": "92b983078f329a96"
    }
  ],
  "817f3bdcbaff1665": [
    {
      "graph_id_type": "dc_id",
      "proprietary_id": "mp-760124",
      "datasource": "MP",
      "url": "https://next-gen.materialsproject.org/materials/mp-760124",
      "filehash": "92b983078f329a96"
    }
  ],
  "261311429735457e": [
    {
      "graph_id_type": "md_id",
      "proprietary_id": "mp-760201",
      "datasource": "MP",
      "url": "https://next-gen.materialsproject.org/materials/mp-760201",
      "filehash": "ccd88582e3c5c1a0"
    }
  ],
  "c2a35dab93f9d2d9": [
    {
      "graph_id_type": "topo_md_id",
      "proprietary_id": "mp-760201",
      "datasource": "MP",
      "url": "https://next-gen.materialsproject.org/materials/mp-760201",
      "filehash": "ccd88582e3c5c1a0"
    }
  ],
  "40f888bb54f841a6": [
    {
      "graph_id_type": "dc_id",
      "proprietary_id": "mp-760201",
      "datasource": "MP",
      "url": "https://next-gen.materialsproject.org/materials/mp-760201",
      "filehash": "ccd88582e3c5c1a0"
    }
  ],
  "4966d119d9ba6162": [
    {
      "graph_id_type": "md_id",
      "proprietary_id": "mp-772104",
      "datasource": "MP",
      "url": "https://next-gen.materialsproject.org/materials/mp-772104",
      "filehash": "83301da25721d446"
    }
  ],
  "0dd5be26aaf758ae": [
    {
      "graph_id_type": "topo_md_id",
      "proprietary_id": "mp-772104",
      "datasource": "MP",
      "url": "https://next-gen.materialsproject.org/materials/mp-772104",
      "filehash": "83301da25721d446"
    }
  ],
  "f2382097e34f4038": [
    {
      "graph_id_type": "dc_id",
      "proprietary_id": "mp-772104",
      "datasource": "MP",
      "url": "https://next-gen.materialsproject.org/materials/mp-772104",
      "filehash": "83301da25721d446"
    }
  ],
  "c12766aacc668429": [
    {
      "graph_id_type": "md_id",
      "proprietary_id": "mp-772112",
      "datasource": "MP",
      "url": "https://next-gen.materialsproject.org/materials/mp-772112",
      "filehash": "1f6bc99e33158dec"
    }
  ],
  "54bb3f42181bd968": [
    {
      "graph_id_type": "topo_md_id",
      "proprietary_id": "mp-772112",
      "datasource": "MP",
      "url": "https://next-gen.materialsproject.org/materials/mp-772112",
      "filehash": "1f6bc99e33158dec"
    }
  ],
  "b6ecfa79f1f1a424": [
    {
      "graph_id_type": "dc_id",
      "proprietary_id": "mp-772112",
      "datasource": "MP",
      "url": "https://next-gen.materialsproject.org/materials/mp-772112",
      "filehash": "1f6bc99e33158dec"
    }
  ],
  "24c2ee46c7446313": [
    {
      "graph_id_type": "md_id",
      "proprietary_id": "mp-772081",
      "datasource": "MP",
      "url": "https://next-gen.materialsproject.org/materials/mp-772081",
      "filehash": "6932288053e45bac"
    }
  ],
  "add73414e4e11318": [
    {
      "graph_id_type": "topo_md_id",
      "proprietary_id": "mp-772081",
      "datasource": "MP",
      "url": "https://next-gen.materialsproject.org/materials/mp-772081",
      "filehash": "6932288053e45bac"
    }
  ],
  "d6013dc9b2c59322": [
    {
      "graph_id_type": "dc_id",
      "proprietary_id": "mp-772081",
      "datasource": "MP",
      "url": "https://next-gen.materialsproject.org/materials/mp-772081",
      "filehash": "6932288053e45bac"
    }
  ],
  "1917b9aa9e2bbe51": [
    {
      "graph_id_type": "md_id",
      "proprietary_id": "mp-772361",
      "datasource": "MP",
      "url": "https://next-gen.materialsproject.org/materials/mp-772361",
      "filehash": "9ebe72e42ff4d680"
    }
  ],
  "9df4cdc12318cd02": [
    {
      "graph_id_type": "topo_md_id",
      "proprietary_id": "mp-772361",
      "datasource": "MP",
      "url": "https://next-gen.materialsproject.org/materials/mp-772361",
      "filehash": "9ebe72e42ff4d680"
    }
  ],
  "a96aad7cf7c59d6c": [
    {
      "graph_id_type": "dc_id",
      "proprietary_id": "mp-772361",
      "datasource": "MP",
      "url": "https://next-gen.materialsproject.org/materials/mp-772361",
      "filehash": "9ebe72e42ff4d680"
    }
  ],
  "388c7e0f7878c082": [
    {
      "graph_id_type": "md_id",
      "proprietary_id": "mp-772196",
      "datasource": "MP",
      "url": "https://next-gen.materialsproject.org/materials/mp-772196",
      "filehash": "16270dd7eb304145"
    }
  ],
  "a832e93aafeecf03": [
    {
      "graph_id_type": "topo_md_id",
      "proprietary_id": "mp-772196",
      "datasource": "MP",
      "url": "https://next-gen.materialsproject.org/materials/mp-772196",
      "filehash": "16270dd7eb304145"
    }
  ],
  "0f17deee891bc71d": [
    {
      "graph_id_type": "dc_id",
      "proprietary_id": "mp-772196",
      "datasource": "MP",
      "url": "https://next-gen.materialsproject.org/materials/mp-772196",
      "filehash": "16270dd7eb304145"
    }
  ],
  "911f55b322a08da3": [
    {
      "graph_id_type": "md_id",
      "proprietary_id": "mp-772719",
      "datasource": "MP",
      "url": "https://next-gen.materialsproject.org/materials/mp-772719",
      "filehash": "4c234c605a75cdae"
    }
  ],
  "1daf8efba8f85514": [
    {
      "graph_id_type": "topo_md_id",
      "proprietary_id": "mp-772719",
      "datasource": "MP",
      "url": "https://next-gen.materialsproject.org/materials/mp-772719",
      "filehash": "4c234c605a75cdae"
    }
  ],
  "fd9103b518a10a72": [
    {
      "graph_id_type": "dc_id",
      "proprietary_id": "mp-772719",
      "datasource": "MP",
      "url": "https://next-gen.materialsproject.org/materials/mp-772719",
      "filehash": "4c234c605a75cdae"
    }
  ],
  "35a6773726739591": [
    {
      "graph_id_type": "md_id",
      "proprietary_id": "mp-772675",
      "datasource": "MP",
      "url": "https://next-gen.materialsproject.org/materials/mp-772675",
      "filehash": "e63551a3effffb16"
    }
  ],
  "b26ff964165d4240": [
    {
      "graph_id_type": "topo_md_id",
      "proprietary_id": "mp-772675",
      "datasource": "MP",
      "url": "https://next-gen.materialsproject.org/materials/mp-772675",
      "filehash": "e63551a3effffb16"
    }
  ],
  "4923460c93a7cb4c": [
    {
      "graph_id_type": "dc_id",
      "proprietary_id": "mp-772675",
      "datasource": "MP",
      "url": "https://next-gen.materialsproject.org/materials/mp-772675",
      "filehash": "e63551a3effffb16"
    }
  ],
  "aa9999e358952e01": [
    {
      "graph_id_type": "md_id",
      "proprietary_id": "mp-772227",
      "datasource": "MP",
      "url": "https://next-gen.materialsproject.org/materials/mp-772227",
      "filehash": "59a859636766e17b"
    }
  ],
  "22d4e3191b4bfe59": [
    {
      "graph_id_type": "topo_md_id",
      "proprietary_id": "mp-772227",
      "datasource": "MP",
      "url": "https://next-gen.materialsproject.org/materials/mp-772227",
      "filehash": "59a859636766e17b"
    }
  ],
  "1e2660df6488cf2d": [
    {
      "graph_id_type": "dc_id",
      "proprietary_id": "mp-772227",
      "datasource": "MP",
      "url": "https://next-gen.materialsproject.org/materials/mp-772227",
      "filehash": "59a859636766e17b"
    }
  ],
  "ef69d7f1b5787898": [
    {
      "graph_id_type": "md_id",
      "proprietary_id": "mp-772642",
      "datasource": "MP",
      "url": "https://next-gen.materialsproject.org/materials/mp-772642",
      "filehash": "2a9be0cc119aa44e"
    }
  ],
  "7730d91d0360fb2e": [
    {
      "graph_id_type": "topo_md_id",
      "proprietary_id": "mp-772642",
      "datasource": "MP",
      "url": "https://next-gen.materialsproject.org/materials/mp-772642",
      "filehash": "2a9be0cc119aa44e"
    }
  ],
  "f08c0fbb468c0a25": [
    {
      "graph_id_type": "dc_id",
      "proprietary_id": "mp-772642",
      "datasource": "MP",
      "url": "https://next-gen.materialsproject.org/materials/mp-772642",
      "filehash": "2a9be0cc119aa44e"
    }
  ],
  "ec868e647f44fd67": [
    {
      "graph_id_type": "md_id",
      "proprietary_id": "mp-772139",
      "datasource": "MP",
      "url": "https://next-gen.materialsproject.org/materials/mp-772139",
      "filehash": "e3549e87a1783867"
    }
  ],
  "8d299189e5d4bd5e": [
    {
      "graph_id_type": "topo_md_id",
      "proprietary_id": "mp-772139",
      "datasource": "MP",
      "url": "https://next-gen.materialsproject.org/materials/mp-772139",
      "filehash": "e3549e87a1783867"
    }
  ],
  "dbf5f12c9d873c97": [
    {
      "graph_id_type": "dc_id",
      "proprietary_id": "mp-772139",
      "datasource": "MP",
      "url": "https://next-gen.materialsproject.org/materials/mp-772139",
      "filehash": "e3549e87a1783867"
    }
  ],
  "4d958fbda7ee47cb": [
    {
      "graph_id_type": "md_id",
      "proprietary_id": "mp-772092",
      "datasource": "MP",
      "url": "https://next-gen.materialsproject.org/materials/mp-772092",
      "filehash": "a343b8dba5bebf43"
    }
  ],
  "16f1df27a6d7e5af": [
    {
      "graph_id_type": "topo_md_id",
      "proprietary_id": "mp-772092",
      "datasource": "MP",
      "url": "https://next-gen.materialsproject.org/materials/mp-772092",
      "filehash": "a343b8dba5bebf43"
    }
  ],
  "1e32b6ae5d2ad01b": [
    {
      "graph_id_type": "dc_id",
      "proprietary_id": "mp-772092",
      "datasource": "MP",
      "url": "https://next-gen.materialsproject.org/materials/mp-772092",
      "filehash": "a343b8dba5bebf43"
    }
  ],
  "b48c556931c59f5d": [
    {
      "graph_id_type": "md_id",
      "proprietary_id": "mp-772075",
      "datasource": "MP",
      "url": "https://next-gen.materialsproject.org/materials/mp-772075",
      "filehash": "4e3b02e2c6c77682"
    }
  ],
  "d0443711732eebf0": [
    {
      "graph_id_type": "topo_md_id",
      "proprietary_id": "mp-772075",
      "datasource": "MP",
      "url": "https://next-gen.materialsproject.org/materials/mp-772075",
      "filehash": "4e3b02e2c6c77682"
    }
  ],
  "8c15bcb5b7537e0b": [
    {
      "graph_id_type": "dc_id",
      "proprietary_id": "mp-772075",
      "datasource": "MP",
      "url": "https://next-gen.materialsproject.org/materials/mp-772075",
      "filehash": "4e3b02e2c6c77682"
    }
  ],
  "7753a1c150a7a04f": [
    {
      "graph_id_type": "md_id",
      "proprietary_id": "mp-772407",
      "datasource": "MP",
      "url": "https://next-gen.materialsproject.org/materials/mp-772407",
      "filehash": "219aafe49e113ce9"
    }
  ],
  "521c10a1ed6a7340": [
    {
      "graph_id_type": "topo_md_id",
      "proprietary_id": "mp-772407",
      "datasource": "MP",
      "url": "https://next-gen.materialsproject.org/materials/mp-772407",
      "filehash": "219aafe49e113ce9"
    }
  ],
  "bb9956f224283b90": [
    {
      "graph_id_type": "dc_id",
      "proprietary_id": "mp-772407",
      "datasource": "MP",
      "url": "https://next-gen.materialsproject.org/materials/mp-772407",
      "filehash": "219aafe49e113ce9"
    }
  ],
  "576cb5b4429ff0d3": [
    {
      "graph_id_type": "md_id",
      "proprietary_id": "mp-772646",
      "datasource": "MP",
      "url": "https://next-gen.materialsproject.org/materials/mp-772646",
      "filehash": "d963085d7259e676"
    }
  ],
  "f1ec71cfafda4741": [
    {
      "graph_id_type": "topo_md_id",
      "proprietary_id": "mp-772646",
      "datasource": "MP",
      "url": "https://next-gen.materialsproject.org/materials/mp-772646",
      "filehash": "d963085d7259e676"
    }
  ],
  "e9a59ff3eae2a63e": [
    {
      "graph_id_type": "dc_id",
      "proprietary_id": "mp-772646",
      "datasource": "MP",
      "url": "https://next-gen.materialsproject.org/materials/mp-772646",
      "filehash": "d963085d7259e676"
    }
  ],
  "0f4705b2138b2faa": [
    {
      "graph_id_type": "md_id",
      "proprietary_id": "mp-760259",
      "datasource": "MP",
      "url": "https://next-gen.materialsproject.org/materials/mp-760259",
      "filehash": "cdb3148cf85db598"
    }
  ],
  "df2d44e1e929f910": [
    {
      "graph_id_type": "topo_md_id",
      "proprietary_id": "mp-760259",
      "datasource": "MP",
      "url": "https://next-gen.materialsproject.org/materials/mp-760259",
      "filehash": "cdb3148cf85db598"
    }
  ],
  "b30cfcd02ad2d322": [
    {
      "graph_id_type": "dc_id",
      "proprietary_id": "mp-760259",
      "datasource": "MP",
      "url": "https://next-gen.materialsproject.org/materials/mp-760259",
      "filehash": "cdb3148cf85db598"
    }
  ],
  "9f2e49789f03e243": [
    {
      "graph_id_type": "md_id",
      "proprietary_id": "mp-760114",
      "datasource": "MP",
      "url": "https://next-gen.materialsproject.org/materials/mp-760114",
      "filehash": "b9de48a26a133188"
    }
  ],
  "a86e9b4f9cf060a5": [
    {
      "graph_id_type": "topo_md_id",
      "proprietary_id": "mp-760114",
      "datasource": "MP",
      "url": "https://next-gen.materialsproject.org/materials/mp-760114",
      "filehash": "b9de48a26a133188"
    }
  ],
  "6685ff7de04696c7": [
    {
      "graph_id_type": "dc_id",
      "proprietary_id": "mp-760114",
      "datasource": "MP",
      "url": "https://next-gen.materialsproject.org/materials/mp-760114",
      "filehash": "b9de48a26a133188"
    }
  ],
  "0b9932c19b87deee": [
    {
      "graph_id_type": "md_id",
      "proprietary_id": "mp-760160",
      "datasource": "MP",
      "url": "https://next-gen.materialsproject.org/materials/mp-760160",
      "filehash": "de93b3601177bd1d"
    }
  ],
  "a2b9bccd2037f59a": [
    {
      "graph_id_type": "topo_md_id",
      "proprietary_id": "mp-760160",
      "datasource": "MP",
      "url": "https://next-gen.materialsproject.org/materials/mp-760160",
      "filehash": "de93b3601177bd1d"
    }
  ],
  "82ba842f363e1e21": [
    {
      "graph_id_type": "dc_id",
      "proprietary_id": "mp-760160",
      "datasource": "MP",
      "url": "https://next-gen.materialsproject.org/materials/mp-760160",
      "filehash": "de93b3601177bd1d"
    }
  ],
  "540611eb65e55b5c": [
    {
      "graph_id_type": "md_id",
      "proprietary_id": "mp-759755",
      "datasource": "MP",
      "url": "https://next-gen.materialsproject.org/materials/mp-759755",
      "filehash": "cb5605fae23f65c5"
    }
  ],
  "ad997d9da79f8067": [
    {
      "graph_id_type": "topo_md_id",
      "proprietary_id": "mp-759755",
      "datasource": "MP",
      "url": "https://next-gen.materialsproject.org/materials/mp-759755",
      "filehash": "cb5605fae23f65c5"
    }
  ],
  "39ab18389a58b4b1": [
    {
      "graph_id_type": "dc_id",
      "proprietary_id": "mp-759755",
      "datasource": "MP",
      "url": "https://next-gen.materialsproject.org/materials/mp-759755",
      "filehash": "cb5605fae23f65c5"
    }
  ],
  "1846d456010cefbf": [
    {
      "graph_id_type": "md_id",
      "proprietary_id": "mp-757184",
      "datasource": "MP",
      "url": "https://next-gen.materialsproject.org/materials/mp-757184",
      "filehash": "edf5ad16e260503f"
    }
  ],
  "c3a587cbe92ed780": [
    {
      "graph_id_type": "topo_md_id",
      "proprietary_id": "mp-757184",
      "datasource": "MP",
      "url": "https://next-gen.materialsproject.org/materials/mp-757184",
      "filehash": "edf5ad16e260503f"
    }
  ],
  "4ef4ea0584400015": [
    {
      "graph_id_type": "dc_id",
      "proprietary_id": "mp-757184",
      "datasource": "MP",
      "url": "https://next-gen.materialsproject.org/materials/mp-757184",
      "filehash": "edf5ad16e260503f"
    }
  ],
  "24465eb7040011b1": [
    {
      "graph_id_type": "md_id",
      "proprietary_id": "mp-757213",
      "datasource": "MP",
      "url": "https://next-gen.materialsproject.org/materials/mp-757213",
      "filehash": "305df676d2c6cb48"
    }
  ],
  "29dcd22467606adb": [
    {
      "graph_id_type": "topo_md_id",
      "proprietary_id": "mp-757213",
      "datasource": "MP",
      "url": "https://next-gen.materialsproject.org/materials/mp-757213",
      "filehash": "305df676d2c6cb48"
    }
  ],
  "435f6849376d76cf": [
    {
      "graph_id_type": "dc_id",
      "proprietary_id": "mp-757213",
      "datasource": "MP",
      "url": "https://next-gen.materialsproject.org/materials/mp-757213",
      "filehash": "305df676d2c6cb48"
    }
  ],
  "e77c50d266034e1b": [
    {
      "graph_id_type": "md_id",
      "proprietary_id": "mp-757517",
      "datasource": "MP",
      "url": "https://next-gen.materialsproject.org/materials/mp-757517",
      "filehash": "990ea978ad296b9d"
    }
  ],
  "746d40529dd8dcbc": [
    {
      "graph_id_type": "topo_md_id",
      "proprietary_id": "mp-757517",
      "datasource": "MP",
      "url": "https://next-gen.materialsproject.org/materials/mp-757517",
      "filehash": "990ea978ad296b9d"
    }
  ],
  "e53447fa242ae696": [
    {
      "graph_id_type": "dc_id",
      "proprietary_id": "mp-757517",
      "datasource": "MP",
      "url": "https://next-gen.materialsproject.org/materials/mp-757517",
      "filehash": "990ea978ad296b9d"
    }
  ],
  "feaa497e01886755": [
    {
      "graph_id_type": "md_id",
      "proprietary_id": "mp-757400",
      "datasource": "MP",
      "url": "https://next-gen.materialsproject.org/materials/mp-757400",
      "filehash": "03fe5d138d84fa91"
    }
  ],
  "a76d7808f5c160de": [
    {
      "graph_id_type": "topo_md_id",
      "proprietary_id": "mp-757400",
      "datasource": "MP",
      "url": "https://next-gen.materialsproject.org/materials/mp-757400",
      "filehash": "03fe5d138d84fa91"
    }
  ],
  "4fb3dc7f2a4ee072": [
    {
      "graph_id_type": "dc_id",
      "proprietary_id": "mp-757400",
      "datasource": "MP",
      "url": "https://next-gen.materialsproject.org/materials/mp-757400",
      "filehash": "03fe5d138d84fa91"
    }
  ],
  "cccaddde47febceb": [
    {
      "graph_id_type": "md_id",
      "proprietary_id": "mp-757217",
      "datasource": "MP",
      "url": "https://next-gen.materialsproject.org/materials/mp-757217",
      "filehash": "db6834f462a494dc"
    }
  ],
  "68482a0b41d1b1e5": [
    {
      "graph_id_type": "topo_md_id",
      "proprietary_id": "mp-757217",
      "datasource": "MP",
      "url": "https://next-gen.materialsproject.org/materials/mp-757217",
      "filehash": "db6834f462a494dc"
    }
  ],
  "40970039786335c0": [
    {
      "graph_id_type": "dc_id",
      "proprietary_id": "mp-757217",
      "datasource": "MP",
      "url": "https://next-gen.materialsproject.org/materials/mp-757217",
      "filehash": "db6834f462a494dc"
    }
  ],
  "2b25cfdc39b5522e": [
    {
      "graph_id_type": "md_id",
      "proprietary_id": "mp-757591",
      "datasource": "MP",
      "url": "https://next-gen.materialsproject.org/materials/mp-757591",
      "filehash": "e2bb29ce48ebd418"
    }
  ],
  "ec6a30a7f8f3437d": [
    {
      "graph_id_type": "topo_md_id",
      "proprietary_id": "mp-757591",
      "datasource": "MP",
      "url": "https://next-gen.materialsproject.org/materials/mp-757591",
      "filehash": "e2bb29ce48ebd418"
    }
  ],
  "0f9986c33890b210": [
    {
      "graph_id_type": "dc_id",
      "proprietary_id": "mp-757591",
      "datasource": "MP",
      "url": "https://next-gen.materialsproject.org/materials/mp-757591",
      "filehash": "e2bb29ce48ebd418"
    }
  ],
  "4052ba9eb654374d": [
    {
      "graph_id_type": "md_id",
      "proprietary_id": "mp-757632",
      "datasource": "MP",
      "url": "https://next-gen.materialsproject.org/materials/mp-757632",
      "filehash": "a5f83e268d1b7f2d"
    }
  ],
  "82c1fd704bd5414f": [
    {
      "graph_id_type": "topo_md_id",
      "proprietary_id": "mp-757632",
      "datasource": "MP",
      "url": "https://next-gen.materialsproject.org/materials/mp-757632",
      "filehash": "a5f83e268d1b7f2d"
    }
  ],
  "299b2af8c1691631": [
    {
      "graph_id_type": "dc_id",
      "proprietary_id": "mp-757632",
      "datasource": "MP",
      "url": "https://next-gen.materialsproject.org/materials/mp-757632",
      "filehash": "a5f83e268d1b7f2d"
    }
  ],
  "0a6b0bc99b9e9452": [
    {
      "graph_id_type": "md_id",
      "proprietary_id": "mp-757882",
      "datasource": "MP",
      "url": "https://next-gen.materialsproject.org/materials/mp-757882",
      "filehash": "3cbca11140c52853"
    }
  ],
  "db20a5bb8e5be46c": [
    {
      "graph_id_type": "topo_md_id",
      "proprietary_id": "mp-757882",
      "datasource": "MP",
      "url": "https://next-gen.materialsproject.org/materials/mp-757882",
      "filehash": "3cbca11140c52853"
    }
  ],
  "7430a90c18d1a0a9": [
    {
      "graph_id_type": "dc_id",
      "proprietary_id": "mp-757882",
      "datasource": "MP",
      "url": "https://next-gen.materialsproject.org/materials/mp-757882",
      "filehash": "3cbca11140c52853"
    }
  ],
  "4b65ea429c2ee277": [
    {
      "graph_id_type": "md_id",
      "proprietary_id": "mp-757536",
      "datasource": "MP",
      "url": "https://next-gen.materialsproject.org/materials/mp-757536",
      "filehash": "bc9fbfd6e32e46a2"
    }
  ],
  "0fc3021126aa4471": [
    {
      "graph_id_type": "topo_md_id",
      "proprietary_id": "mp-757536",
      "datasource": "MP",
      "url": "https://next-gen.materialsproject.org/materials/mp-757536",
      "filehash": "bc9fbfd6e32e46a2"
    }
  ],
  "84b785ea35b480c2": [
    {
      "graph_id_type": "dc_id",
      "proprietary_id": "mp-757536",
      "datasource": "MP",
      "url": "https://next-gen.materialsproject.org/materials/mp-757536",
      "filehash": "bc9fbfd6e32e46a2"
    }
  ],
  "8319ad8242ef0390": [
    {
      "graph_id_type": "md_id",
      "proprietary_id": "mp-757631",
      "datasource": "MP",
      "url": "https://next-gen.materialsproject.org/materials/mp-757631",
      "filehash": "8e14815fd9021366"
    }
  ],
  "526205941314b8cf": [
    {
      "graph_id_type": "topo_md_id",
      "proprietary_id": "mp-757631",
      "datasource": "MP",
      "url": "https://next-gen.materialsproject.org/materials/mp-757631",
      "filehash": "8e14815fd9021366"
    }
  ],
  "ef0930da955fc9af": [
    {
      "graph_id_type": "dc_id",
      "proprietary_id": "mp-757631",
      "datasource": "MP",
      "url": "https://next-gen.materialsproject.org/materials/mp-757631",
      "filehash": "8e14815fd9021366"
    }
  ],
  "b2fac83c405a5308": [
    {
      "graph_id_type": "md_id",
      "proprietary_id": "mp-772026",
      "datasource": "MP",
      "url": "https://next-gen.materialsproject.org/materials/mp-772026",
      "filehash": "0d03214755e142a2"
    }
  ],
  "8b97fce2b0ebfc6f": [
    {
      "graph_id_type": "topo_md_id",
      "proprietary_id": "mp-772026",
      "datasource": "MP",
      "url": "https://next-gen.materialsproject.org/materials/mp-772026",
      "filehash": "0d03214755e142a2"
    }
  ],
  "0dbee9effe6f978e": [
    {
      "graph_id_type": "dc_id",
      "proprietary_id": "mp-772026",
      "datasource": "MP",
      "url": "https://next-gen.materialsproject.org/materials/mp-772026",
      "filehash": "0d03214755e142a2"
    }
  ],
  "be13053f0a03ed84": [
    {
      "graph_id_type": "md_id",
      "proprietary_id": "mp-771874",
      "datasource": "MP",
      "url": "https://next-gen.materialsproject.org/materials/mp-771874",
      "filehash": "cda1c0b7e00e9ef6"
    }
  ],
  "9a6c7ae740eefb03": [
    {
      "graph_id_type": "topo_md_id",
      "proprietary_id": "mp-771874",
      "datasource": "MP",
      "url": "https://next-gen.materialsproject.org/materials/mp-771874",
      "filehash": "cda1c0b7e00e9ef6"
    }
  ],
  "572e0fcd58b905f6": [
    {
      "graph_id_type": "dc_id",
      "proprietary_id": "mp-771874",
      "datasource": "MP",
      "url": "https://next-gen.materialsproject.org/materials/mp-771874",
      "filehash": "cda1c0b7e00e9ef6"
    }
  ],
  "9b5764c9ae66d29d": [
    {
      "graph_id_type": "md_id",
      "proprietary_id": "mp-771835",
      "datasource": "MP",
      "url": "https://next-gen.materialsproject.org/materials/mp-771835",
      "filehash": "875900bda84448c5"
    }
  ],
  "4147040c7acea4d9": [
    {
      "graph_id_type": "topo_md_id",
      "proprietary_id": "mp-771835",
      "datasource": "MP",
      "url": "https://next-gen.materialsproject.org/materials/mp-771835",
      "filehash": "875900bda84448c5"
    }
  ],
  "b7e5a7a5998d4c74": [
    {
      "graph_id_type": "dc_id",
      "proprietary_id": "mp-771835",
      "datasource": "MP",
      "url": "https://next-gen.materialsproject.org/materials/mp-771835",
      "filehash": "875900bda84448c5"
    }
  ],
  "95107c23c5c4dc00": [
    {
      "graph_id_type": "md_id",
      "proprietary_id": "mp-772078",
      "datasource": "MP",
      "url": "https://next-gen.materialsproject.org/materials/mp-772078",
      "filehash": "bf5d9f9238c29f23"
    }
  ],
  "3b3f0e93c9531cb3": [
    {
      "graph_id_type": "topo_md_id",
      "proprietary_id": "mp-772078",
      "datasource": "MP",
      "url": "https://next-gen.materialsproject.org/materials/mp-772078",
      "filehash": "bf5d9f9238c29f23"
    }
  ],
  "f7308c375722d3b2": [
    {
      "graph_id_type": "dc_id",
      "proprietary_id": "mp-772078",
      "datasource": "MP",
      "url": "https://next-gen.materialsproject.org/materials/mp-772078",
      "filehash": "bf5d9f9238c29f23"
    }
  ],
  "75c5c60ecf68f728": [
    {
      "graph_id_type": "md_id",
      "proprietary_id": "mp-1176900",
      "datasource": "MP",
      "url": "https://next-gen.materialsproject.org/materials/mp-1176900",
      "filehash": "7013476426cea87e"
    }
  ],
  "a24612134c64ef8c": [
    {
      "graph_id_type": "topo_md_id",
      "proprietary_id": "mp-1176900",
      "datasource": "MP",
      "url": "https://next-gen.materialsproject.org/materials/mp-1176900",
      "filehash": "7013476426cea87e"
    }
  ],
  "a43d78e21b5593c4": [
    {
      "graph_id_type": "dc_id",
      "proprietary_id": "mp-1176900",
      "datasource": "MP",
      "url": "https://next-gen.materialsproject.org/materials/mp-1176900",
      "filehash": "7013476426cea87e"
    }
  ],
  "2b381befc4a292ac": [
    {
      "graph_id_type": "md_id",
      "proprietary_id": "mp-1176896",
      "datasource": "MP",
      "url": "https://next-gen.materialsproject.org/materials/mp-1176896",
      "filehash": "169bfc10ac22c50e"
    }
  ],
  "1faa2a10750a8ec1": [
    {
      "graph_id_type": "topo_md_id",
      "proprietary_id": "mp-1176896",
      "datasource": "MP",
      "url": "https://next-gen.materialsproject.org/materials/mp-1176896",
      "filehash": "169bfc10ac22c50e"
    }
  ],
  "0b5bda7e2f9d9cb1": [
    {
      "graph_id_type": "dc_id",
      "proprietary_id": "mp-1176896",
      "datasource": "MP",
      "url": "https://next-gen.materialsproject.org/materials/mp-1176896",
      "filehash": "169bfc10ac22c50e"
    }
  ],
  "357e98480c553063": [
    {
      "graph_id_type": "md_id",
      "proprietary_id": "mp-760182",
      "datasource": "MP",
      "url": "https://next-gen.materialsproject.org/materials/mp-760182",
      "filehash": "46c19a6a93d4a0cf"
    }
  ],
  "61459f8867de3f0f": [
    {
      "graph_id_type": "topo_md_id",
      "proprietary_id": "mp-760182",
      "datasource": "MP",
      "url": "https://next-gen.materialsproject.org/materials/mp-760182",
      "filehash": "46c19a6a93d4a0cf"
    }
  ],
  "687c143b0fc236fa": [
    {
      "graph_id_type": "dc_id",
      "proprietary_id": "mp-760182",
      "datasource": "MP",
      "url": "https://next-gen.materialsproject.org/materials/mp-760182",
      "filehash": "46c19a6a93d4a0cf"
    }
  ],
  "ccf063ba31f00f32": [
    {
      "graph_id_type": "md_id",
      "proprietary_id": "mp-1176947",
      "datasource": "MP",
      "url": "https://next-gen.materialsproject.org/materials/mp-1176947",
      "filehash": "07275de48144e63c"
    }
  ],
  "9e54b9584aa5addf": [
    {
      "graph_id_type": "topo_md_id",
      "proprietary_id": "mp-1176947",
      "datasource": "MP",
      "url": "https://next-gen.materialsproject.org/materials/mp-1176947",
      "filehash": "07275de48144e63c"
    }
  ],
  "5b9e49dc4cb9a952": [
    {
      "graph_id_type": "dc_id",
      "proprietary_id": "mp-1176947",
      "datasource": "MP",
      "url": "https://next-gen.materialsproject.org/materials/mp-1176947",
      "filehash": "07275de48144e63c"
    }
  ],
  "3f8a3c1eadb04aa0": [
    {
      "graph_id_type": "md_id",
      "proprietary_id": "mp-772557",
      "datasource": "MP",
      "url": "https://next-gen.materialsproject.org/materials/mp-772557",
      "filehash": "8eb6a3a1f25efcbe"
    }
  ],
  "f3f34541d1cf27e1": [
    {
      "graph_id_type": "topo_md_id",
      "proprietary_id": "mp-772557",
      "datasource": "MP",
      "url": "https://next-gen.materialsproject.org/materials/mp-772557",
      "filehash": "8eb6a3a1f25efcbe"
    }
  ],
  "5f57a5eeea44aace": [
    {
      "graph_id_type": "dc_id",
      "proprietary_id": "mp-772557",
      "datasource": "MP",
      "url": "https://next-gen.materialsproject.org/materials/mp-772557",
      "filehash": "8eb6a3a1f25efcbe"
    }
  ],
  "539f5ca30c5cf2a7": [
    {
      "graph_id_type": "md_id",
      "proprietary_id": "mp-1176905",
      "datasource": "MP",
      "url": "https://next-gen.materialsproject.org/materials/mp-1176905",
      "filehash": "3a53248ecd1568ff"
    }
  ],
  "6945c3ed2d048128": [
    {
      "graph_id_type": "topo_md_id",
      "proprietary_id": "mp-1176905",
      "datasource": "MP",
      "url": "https://next-gen.materialsproject.org/materials/mp-1176905",
      "filehash": "3a53248ecd1568ff"
    }
  ],
  "490be32e914585ea": [
    {
      "graph_id_type": "dc_id",
      "proprietary_id": "mp-1176905",
      "datasource": "MP",
      "url": "https://next-gen.materialsproject.org/materials/mp-1176905",
      "filehash": "3a53248ecd1568ff"
    }
  ],
  "de1e7ccd8a643f85": [
    {
      "graph_id_type": "md_id",
      "proprietary_id": "mp-1176904",
      "datasource": "MP",
      "url": "https://next-gen.materialsproject.org/materials/mp-1176904",
      "filehash": "177b192166120876"
    }
  ],
  "37189100f071c79f": [
    {
      "graph_id_type": "topo_md_id",
      "proprietary_id": "mp-1176904",
      "datasource": "MP",
      "url": "https://next-gen.materialsproject.org/materials/mp-1176904",
      "filehash": "177b192166120876"
    }
  ],
  "fa4a498631b06409": [
    {
      "graph_id_type": "dc_id",
      "proprietary_id": "mp-1176904",
      "datasource": "MP",
      "url": "https://next-gen.materialsproject.org/materials/mp-1176904",
      "filehash": "177b192166120876"
    }
  ],
  "884dc5b09d9f96cc": [
    {
      "graph_id_type": "md_id",
      "proprietary_id": "mp-1176903",
      "datasource": "MP",
      "url": "https://next-gen.materialsproject.org/materials/mp-1176903",
      "filehash": "38945db1efc4d22e"
    }
  ],
  "8d6a27a6cb2027d5": [
    {
      "graph_id_type": "topo_md_id",
      "proprietary_id": "mp-1176903",
      "datasource": "MP",
      "url": "https://next-gen.materialsproject.org/materials/mp-1176903",
      "filehash": "38945db1efc4d22e"
    }
  ],
  "64dd7109e986b266": [
    {
      "graph_id_type": "dc_id",
      "proprietary_id": "mp-1176903",
      "datasource": "MP",
      "url": "https://next-gen.materialsproject.org/materials/mp-1176903",
      "filehash": "38945db1efc4d22e"
    }
  ],
  "e0f234d732b74569": [
    {
      "graph_id_type": "md_id",
      "proprietary_id": "mp-1176909",
      "datasource": "MP",
      "url": "https://next-gen.materialsproject.org/materials/mp-1176909",
      "filehash": "4963434520f8413a"
    }
  ],
  "345b8f370c97a225": [
    {
      "graph_id_type": "topo_md_id",
      "proprietary_id": "mp-1176909",
      "datasource": "MP",
      "url": "https://next-gen.materialsproject.org/materials/mp-1176909",
      "filehash": "4963434520f8413a"
    }
  ],
  "2f9ddada2298b109": [
    {
      "graph_id_type": "dc_id",
      "proprietary_id": "mp-1176909",
      "datasource": "MP",
      "url": "https://next-gen.materialsproject.org/materials/mp-1176909",
      "filehash": "4963434520f8413a"
    }
  ],
  "2705b955bac1dd9d": [
    {
      "graph_id_type": "md_id",
      "proprietary_id": "mp-1176998",
      "datasource": "MP",
      "url": "https://next-gen.materialsproject.org/materials/mp-1176998",
      "filehash": "d3232d55ccd6c8ef"
    }
  ],
  "d19659fb0ca855e9": [
    {
      "graph_id_type": "topo_md_id",
      "proprietary_id": "mp-1176998",
      "datasource": "MP",
      "url": "https://next-gen.materialsproject.org/materials/mp-1176998",
      "filehash": "d3232d55ccd6c8ef"
    }
  ],
  "993e4abcd0807598": [
    {
      "graph_id_type": "dc_id",
      "proprietary_id": "mp-1176998",
      "datasource": "MP",
      "url": "https://next-gen.materialsproject.org/materials/mp-1176998",
      "filehash": "d3232d55ccd6c8ef"
    }
  ],
  "f098c3e1aa0c84bf": [
    {
      "graph_id_type": "md_id",
      "proprietary_id": "mp-760070",
      "datasource": "MP",
      "url": "https://next-gen.materialsproject.org/materials/mp-760070",
      "filehash": "94ea2556a9bfacc8"
    }
  ],
  "81d942367944a6c4": [
    {
      "graph_id_type": "topo_md_id",
      "proprietary_id": "mp-760070",
      "datasource": "MP",
      "url": "https://next-gen.materialsproject.org/materials/mp-760070",
      "filehash": "94ea2556a9bfacc8"
    }
  ],
  "775fee79d4534aeb": [
    {
      "graph_id_type": "dc_id",
      "proprietary_id": "mp-760070",
      "datasource": "MP",
      "url": "https://next-gen.materialsproject.org/materials/mp-760070",
      "filehash": "94ea2556a9bfacc8"
    }
  ],
  "d04abee896b323bb": [
    {
      "graph_id_type": "md_id",
      "proprietary_id": "mp-1176913",
      "datasource": "MP",
      "url": "https://next-gen.materialsproject.org/materials/mp-1176913",
      "filehash": "9bef36dfb166c324"
    }
  ],
  "60b179ea8df55676": [
    {
      "graph_id_type": "topo_md_id",
      "proprietary_id": "mp-1176913",
      "datasource": "MP",
      "url": "https://next-gen.materialsproject.org/materials/mp-1176913",
      "filehash": "9bef36dfb166c324"
    }
  ],
  "3662d06f94dbd99d": [
    {
      "graph_id_type": "dc_id",
      "proprietary_id": "mp-1176913",
      "datasource": "MP",
      "url": "https://next-gen.materialsproject.org/materials/mp-1176913",
      "filehash": "9bef36dfb166c324"
    }
  ],
  "0cb9f7d54755ab4b": [
    {
      "graph_id_type": "md_id",
      "proprietary_id": "mp-1177035",
      "datasource": "MP",
      "url": "https://next-gen.materialsproject.org/materials/mp-1177035",
      "filehash": "2011975091f5130f"
    }
  ],
  "37ddf72c9b7f1300": [
    {
      "graph_id_type": "topo_md_id",
      "proprietary_id": "mp-1177035",
      "datasource": "MP",
      "url": "https://next-gen.materialsproject.org/materials/mp-1177035",
      "filehash": "2011975091f5130f"
    }
  ],
  "4f6b8b3ddf0595bf": [
    {
      "graph_id_type": "dc_id",
      "proprietary_id": "mp-1177035",
      "datasource": "MP",
      "url": "https://next-gen.materialsproject.org/materials/mp-1177035",
      "filehash": "2011975091f5130f"
    }
  ],
  "09145c85219d1aad": [
    {
      "graph_id_type": "md_id",
      "proprietary_id": "mp-1176902",
      "datasource": "MP",
      "url": "https://next-gen.materialsproject.org/materials/mp-1176902",
      "filehash": "52df1343b01dee18"
    }
  ],
  "6560f5ed3d542ce0": [
    {
      "graph_id_type": "topo_md_id",
      "proprietary_id": "mp-1176902",
      "datasource": "MP",
      "url": "https://next-gen.materialsproject.org/materials/mp-1176902",
      "filehash": "52df1343b01dee18"
    }
  ],
  "7c6370c09862766c": [
    {
      "graph_id_type": "dc_id",
      "proprietary_id": "mp-1176902",
      "datasource": "MP",
      "url": "https://next-gen.materialsproject.org/materials/mp-1176902",
      "filehash": "52df1343b01dee18"
    }
  ],
  "b022e0c6f5e1890f": [
    {
      "graph_id_type": "md_id",
      "proprietary_id": "mp-1177071",
      "datasource": "MP",
      "url": "https://next-gen.materialsproject.org/materials/mp-1177071",
      "filehash": "172f0c4cd6d344fc"
    }
  ],
  "8a7a655eead10d40": [
    {
      "graph_id_type": "topo_md_id",
      "proprietary_id": "mp-1177071",
      "datasource": "MP",
      "url": "https://next-gen.materialsproject.org/materials/mp-1177071",
      "filehash": "172f0c4cd6d344fc"
    }
  ],
  "8cf946f01ca96233": [
    {
      "graph_id_type": "dc_id",
      "proprietary_id": "mp-1177071",
      "datasource": "MP",
      "url": "https://next-gen.materialsproject.org/materials/mp-1177071",
      "filehash": "172f0c4cd6d344fc"
    }
  ],
  "b07b302a79a1b025": [
    {
      "graph_id_type": "md_id",
      "proprietary_id": "mp-1176906",
      "datasource": "MP",
      "url": "https://next-gen.materialsproject.org/materials/mp-1176906",
      "filehash": "06d53ee645d1c0d4"
    }
  ],
  "a0912d6569ac4459": [
    {
      "graph_id_type": "topo_md_id",
      "proprietary_id": "mp-1176906",
      "datasource": "MP",
      "url": "https://next-gen.materialsproject.org/materials/mp-1176906",
      "filehash": "06d53ee645d1c0d4"
    }
  ],
  "223b9e9b55d5803d": [
    {
      "graph_id_type": "dc_id",
      "proprietary_id": "mp-1176906",
      "datasource": "MP",
      "url": "https://next-gen.materialsproject.org/materials/mp-1176906",
      "filehash": "06d53ee645d1c0d4"
    }
  ],
  "27e175e92385e778": [
    {
      "graph_id_type": "md_id",
      "proprietary_id": "mp-504367",
      "datasource": "MP",
      "url": "https://next-gen.materialsproject.org/materials/mp-504367",
      "filehash": "7771146d9f9835d2"
    }
  ],
  "6dfacab226e57b0e": [
    {
      "graph_id_type": "topo_md_id",
      "proprietary_id": "mp-504367",
      "datasource": "MP",
      "url": "https://next-gen.materialsproject.org/materials/mp-504367",
      "filehash": "7771146d9f9835d2"
    }
  ],
  "349483f9d1951faf": [
    {
      "graph_id_type": "dc_id",
      "proprietary_id": "mp-504367",
      "datasource": "MP",
      "url": "https://next-gen.materialsproject.org/materials/mp-504367",
      "filehash": "7771146d9f9835d2"
    }
  ],
  "8783112695974662": [
    {
      "graph_id_type": "md_id",
      "proprietary_id": "mp-757509",
      "datasource": "MP",
      "url": "https://next-gen.materialsproject.org/materials/mp-757509",
      "filehash": "66268a70eb48ef98"
    }
  ],
  "8f0b6dabc019cb65": [
    {
      "graph_id_type": "topo_md_id",
      "proprietary_id": "mp-757509",
      "datasource": "MP",
      "url": "https://next-gen.materialsproject.org/materials/mp-757509",
      "filehash": "66268a70eb48ef98"
    }
  ],
  "ac9798df889c634d": [
    {
      "graph_id_type": "dc_id",
      "proprietary_id": "mp-757509",
      "datasource": "MP",
      "url": "https://next-gen.materialsproject.org/materials/mp-757509",
      "filehash": "66268a70eb48ef98"
    }
  ],
  "b128c2eae48e9130": [
    {
      "graph_id_type": "md_id",
      "proprietary_id": "mp-772239",
      "datasource": "MP",
      "url": "https://next-gen.materialsproject.org/materials/mp-772239",
      "filehash": "49bfe1ede5c93adc"
    }
  ],
  "e13bff9a4b13cc89": [
    {
      "graph_id_type": "topo_md_id",
      "proprietary_id": "mp-772239",
      "datasource": "MP",
      "url": "https://next-gen.materialsproject.org/materials/mp-772239",
      "filehash": "49bfe1ede5c93adc"
    }
  ],
  "3ef988325c3da5a0": [
    {
      "graph_id_type": "dc_id",
      "proprietary_id": "mp-772239",
      "datasource": "MP",
      "url": "https://next-gen.materialsproject.org/materials/mp-772239",
      "filehash": "49bfe1ede5c93adc"
    }
  ],
  "6fbcd0463838967f": [
    {
      "graph_id_type": "md_id",
      "proprietary_id": "mp-773684",
      "datasource": "MP",
      "url": "https://next-gen.materialsproject.org/materials/mp-773684",
      "filehash": "1ab1b4ff3414c519"
    }
  ],
  "97929ce75e7ba651": [
    {
      "graph_id_type": "topo_md_id",
      "proprietary_id": "mp-773684",
      "datasource": "MP",
      "url": "https://next-gen.materialsproject.org/materials/mp-773684",
      "filehash": "1ab1b4ff3414c519"
    }
  ],
  "91b938522969c33a": [
    {
      "graph_id_type": "dc_id",
      "proprietary_id": "mp-773684",
      "datasource": "MP",
      "url": "https://next-gen.materialsproject.org/materials/mp-773684",
      "filehash": "1ab1b4ff3414c519"
    }
  ]
}