{
  "ce27fdbf00cacdd5": [
    {
      "graph_id_type": "md_id",
      "proprietary_id": "mp-1021737",
      "datasource": "MP",
      "url": "https://next-gen.materialsproject.org/materials/mp-1021737",
      "filehash": "61c6a189a6e9e4587ce176f8a97071a2982bbd663c96493544a0c7e1a24ca37b"
    }
  ],
  "4c33810027825913": [
    {
      "graph_id_type": "topo_md_id",
      "proprietary_id": "mp-1021737",
      "datasource": "MP",
      "url": "https://next-gen.materialsproject.org/materials/mp-1021737",
      "filehash": "61c6a189a6e9e4587ce176f8a97071a2982bbd663c96493544a0c7e1a24ca37b"
    }
  ],
  "a25d900a43fd8ef2": [
    {
      "graph_id_type": "dc_id",
      "proprietary_id": "mp-1021737",
      "datasource": "MP",
      "url": "https://next-gen.materialsproject.org/materials/mp-1021737",
      "filehash": "61c6a189a6e9e4587ce176f8a97071a2982bbd663c96493544a0c7e1a24ca37b"
    }
  ],
  "3d8148b4a2580c4b": [
    {
      "graph_id_type": "md_id",
      "proprietary_id": "mp-1021897",
      "datasource": "MP",
      "url": "https://next-gen.materialsproject.org/materials/mp-1021897",
      "filehash": "ac4cb2cf65b05df0e4d4bcc849b73ab51930bcc14a27e3c9eea38e5c44782a20"
    }
  ],
  "3a377bb551c62779": [
    {
      "graph_id_type": "topo_md_id",
      "proprietary_id": "mp-1021897",
      "datasource": "MP",
      "url": "https://next-gen.materialsproject.org/materials/mp-1021897",
      "filehash": "ac4cb2cf65b05df0e4d4bcc849b73ab51930bcc14a27e3c9eea38e5c44782a20"
    }
  ],
  "37b797a8f505645c": [
    {
      "graph_id_type": "dc_id",
      "proprietary_id": "mp-1021897",
      "datasource": "MP",
      "url": "https://next-gen.materialsproject.org/materials/mp-1021897",
      "filehash": "ac4cb2cf65b05df0e4d4bcc849b73ab51930bcc14a27e3c9eea38e5c44782a20"
    }
  ]
}