{
  "6f0e46790044cfdb": [
    {
      "graph_id_type": "md_id",
      "proprietary_id": "mp-1211477",
      "datasource": "MP",
      "url": "https://next-gen.materialsproject.org/materials/mp-1211477",
      "filehash": "71a1604a2472be864ecc846722a19c6e374e2eea50b2c6b1df2bce2daa17843c"
    }
  ],
  "90f20b685c0655b0": [
    {
      "graph_id_type": "topo_md_id",
      "proprietary_id": "mp-1211477",
      "datasource": "MP",
      "url": "https://next-gen.materialsproject.org/materials/mp-1211477",
      "filehash": "71a1604a2472be864ecc846722a19c6e374e2eea50b2c6b1df2bce2daa17843c"
    }
  ],
  "a0171f240b492380": [
    {
      "graph_id_type": "dc_id",
      "proprietary_id": "mp-1211477",
      "datasource": "MP",
      "url": "https://next-gen.materialsproject.org/materials/mp-1211477",
      "filehash": "71a1604a2472be864ecc846722a19c6e374e2eea50b2c6b1df2bce2daa17843c"
    }
  ]
}