{
  "da0b8d37231e1f61": [
    {
      "graph_id_type": "md_id",
      "proprietary_id": "mp-1112982",
      "datasource": "MP",
      "url": "https://next-gen.materialsproject.org/materials/mp-1112982",
      "filehash": "dce44b23f5df3e4ec2e7a31c7da2bc402d6e9b858194a49330cba96ad057ae7d"
    }
  ],
  "8ea938c870d61184": [
    {
      "graph_id_type": "topo_md_id",
      "proprietary_id": "mp-1112982",
      "datasource": "MP",
      "url": "https://next-gen.materialsproject.org/materials/mp-1112982",
      "filehash": "dce44b23f5df3e4ec2e7a31c7da2bc402d6e9b858194a49330cba96ad057ae7d"
    }
  ],
  "58e35bb28053d549": [
    {
      "graph_id_type": "dc_id",
      "proprietary_id": "mp-1112982",
      "datasource": "MP",
      "url": "https://next-gen.materialsproject.org/materials/mp-1112982",
      "filehash": "dce44b23f5df3e4ec2e7a31c7da2bc402d6e9b858194a49330cba96ad057ae7d"
    }
  ]
}