{
  "61ef51973d81b2c3": [
    {
      "graph_id_type": "md_id",
      "proprietary_id": "mp-1106032",
      "datasource": "MP",
      "url": "https://next-gen.materialsproject.org/materials/mp-1106032",
      "filehash": "f0f0cdd5a4dc27ce01cea7367cb6d2a872b3e99808b97c43f0bd310dd5bfb5e5"
    }
  ],
  "d604be90b203cf55": [
    {
      "graph_id_type": "topo_md_id",
      "proprietary_id": "mp-1106032",
      "datasource": "MP",
      "url": "https://next-gen.materialsproject.org/materials/mp-1106032",
      "filehash": "f0f0cdd5a4dc27ce01cea7367cb6d2a872b3e99808b97c43f0bd310dd5bfb5e5"
    }
  ],
  "a9a61f81f91970de": [
    {
      "graph_id_type": "dc_id",
      "proprietary_id": "mp-1106032",
      "datasource": "MP",
      "url": "https://next-gen.materialsproject.org/materials/mp-1106032",
      "filehash": "f0f0cdd5a4dc27ce01cea7367cb6d2a872b3e99808b97c43f0bd310dd5bfb5e5"
    }
  ]
}