{
  "75477e7e03fa838f": [
    {
      "graph_id_type": "md_id",
      "proprietary_id": "mp-1222792",
      "datasource": "MP",
      "url": "https://next-gen.materialsproject.org/materials/mp-1222792",
      "filehash": "374b088743cde6be00f5106c08fae3f2cb181c15676f200a73e0783f24649545"
    }
  ],
  "115fa567104dd10e": [
    {
      "graph_id_type": "topo_md_id",
      "proprietary_id": "mp-1222792",
      "datasource": "MP",
      "url": "https://next-gen.materialsproject.org/materials/mp-1222792",
      "filehash": "374b088743cde6be00f5106c08fae3f2cb181c15676f200a73e0783f24649545"
    }
  ],
  "583dad4d0b70ed98": [
    {
      "graph_id_type": "dc_id",
      "proprietary_id": "mp-1222792",
      "datasource": "MP",
      "url": "https://next-gen.materialsproject.org/materials/mp-1222792",
      "filehash": "374b088743cde6be00f5106c08fae3f2cb181c15676f200a73e0783f24649545"
    }
  ]
}