{
  "ba1bc77f0dd7ba5e": [
    {
      "graph_id_type": "md_id",
      "proprietary_id": "mp-20652",
      "datasource": "MP",
      "url": "https://next-gen.materialsproject.org/materials/mp-20652",
      "filehash": "b048c452e1dc89b18c6eed27b7264c6eced267c03c2f091046d04852ba357b2f"
    }
  ],
  "f110544c0d816ca9": [
    {
      "graph_id_type": "topo_md_id",
      "proprietary_id": "mp-20652",
      "datasource": "MP",
      "url": "https://next-gen.materialsproject.org/materials/mp-20652",
      "filehash": "b048c452e1dc89b18c6eed27b7264c6eced267c03c2f091046d04852ba357b2f"
    }
  ],
  "e8c9d2e3c14f4fba": [
    {
      "graph_id_type": "dc_id",
      "proprietary_id": "mp-20652",
      "datasource": "MP",
      "url": "https://next-gen.materialsproject.org/materials/mp-20652",
      "filehash": "b048c452e1dc89b18c6eed27b7264c6eced267c03c2f091046d04852ba357b2f"
    }
  ]
}