{
  "1c77c77c6bab9e96": [
    {
      "graph_id_type": "md_id",
      "proprietary_id": "mp-574663",
      "datasource": "MP",
      "url": "https://next-gen.materialsproject.org/materials/mp-574663",
      "filehash": "82795ef407992741"
    },
    {
      "graph_id_type": "md_id",
      "proprietary_id": "mp-567336",
      "datasource": "MP",
      "url": "https://next-gen.materialsproject.org/materials/mp-567336",
      "filehash": "8243b4d45f904b5a"
    },
    {
      "graph_id_type": "md_id",
      "proprietary_id": "mp-680111",
      "datasource": "MP",
      "url": "https://next-gen.materialsproject.org/materials/mp-680111",
      "filehash": "a55cedcb2cfbc9d6"
    },
    {
      "graph_id_type": "md_id",
      "proprietary_id": "mp-573608",
      "datasource": "MP",
      "url": "https://next-gen.materialsproject.org/materials/mp-573608",
      "filehash": "861e78dcf75117b4"
    },
    {
      "graph_id_type": "md_id",
      "proprietary_id": "mp-573588",
      "datasource": "MP",
      "url": "https://next-gen.materialsproject.org/materials/mp-573588",
      "filehash": "7598471ad712d30e"
    },
    {
      "graph_id_type": "md_id",
      "proprietary_id": "mp-569994",
      "datasource": "MP",
      "url": "https://next-gen.materialsproject.org/materials/mp-569994",
      "filehash": "d1f010de428f8a5c"
    }
  ],
  "784ee6007bf8d051": [
    {
      "graph_id_type": "topo_md_id",
      "proprietary_id": "mp-574663",
      "datasource": "MP",
      "url": "https://next-gen.materialsproject.org/materials/mp-574663",
      "filehash": "82795ef407992741"
    },
    {
      "graph_id_type": "topo_md_id",
      "proprietary_id": "mp-567336",
      "datasource": "MP",
      "url": "https://next-gen.materialsproject.org/materials/mp-567336",
      "filehash": "8243b4d45f904b5a"
    },
    {
      "graph_id_type": "topo_md_id",
      "proprietary_id": "mp-680111",
      "datasource": "MP",
      "url": "https://next-gen.materialsproject.org/materials/mp-680111",
      "filehash": "a55cedcb2cfbc9d6"
    },
    {
      "graph_id_type": "topo_md_id",
      "proprietary_id": "mp-573608",
      "datasource": "MP",
      "url": "https://next-gen.materialsproject.org/materials/mp-573608",
      "filehash": "861e78dcf75117b4"
    },
    {
      "graph_id_type": "topo_md_id",
      "proprietary_id": "mp-573588",
      "datasource": "MP",
      "url": "https://next-gen.materialsproject.org/materials/mp-573588",
      "filehash": "7598471ad712d30e"
    },
    {
      "graph_id_type": "topo_md_id",
      "proprietary_id": "mp-569994",
      "datasource": "MP",
      "url": "https://next-gen.materialsproject.org/materials/mp-569994",
      "filehash": "d1f010de428f8a5c"
    }
  ],
  "710c70b788228e31": [
    {
      "graph_id_type": "dc_id",
      "proprietary_id": "mp-574663",
      "datasource": "MP",
      "url": "https://next-gen.materialsproject.org/materials/mp-574663",
      "filehash": "82795ef407992741"
    }
  ],
  "47ca1c239fd52a69": [
    {
      "graph_id_type": "dc_id",
      "proprietary_id": "mp-567336",
      "datasource": "MP",
      "url": "https://next-gen.materialsproject.org/materials/mp-567336",
      "filehash": "8243b4d45f904b5a"
    }
  ],
  "b24b40074b2f3bba": [
    {
      "graph_id_type": "dc_id",
      "proprietary_id": "mp-680111",
      "datasource": "MP",
      "url": "https://next-gen.materialsproject.org/materials/mp-680111",
      "filehash": "a55cedcb2cfbc9d6"
    },
    {
      "graph_id_type": "dc_id",
      "proprietary_id": "mp-573608",
      "datasource": "MP",
      "url": "https://next-gen.materialsproject.org/materials/mp-573608",
      "filehash": "861e78dcf75117b4"
    },
    {
      "graph_id_type": "dc_id",
      "proprietary_id": "mp-573588",
      "datasource": "MP",
      "url": "https://next-gen.materialsproject.org/materials/mp-573588",
      "filehash": "7598471ad712d30e"
    },
    {
      "graph_id_type": "dc_id",
      "proprietary_id": "mp-569994",
      "datasource": "MP",
      "url": "https://next-gen.materialsproject.org/materials/mp-569994",
      "filehash": "d1f010de428f8a5c"
    }
  ]
}