{
  "d1162a7d1d06bc1f": [
    {
      "graph_id_type": "md_id",
      "proprietary_id": "mp-1226762",
      "datasource": "MP",
      "url": "https://next-gen.materialsproject.org/materials/mp-1226762",
      "filehash": "c0d4e029f2d980ad"
    }
  ],
  "6ddc6857a1cebb13": [
    {
      "graph_id_type": "topo_md_id",
      "proprietary_id": "mp-1226762",
      "datasource": "MP",
      "url": "https://next-gen.materialsproject.org/materials/mp-1226762",
      "filehash": "c0d4e029f2d980ad"
    }
  ],
  "81d91b0e37afa926": [
    {
      "graph_id_type": "dc_id",
      "proprietary_id": "mp-1226762",
      "datasource": "MP",
      "url": "https://next-gen.materialsproject.org/materials/mp-1226762",
      "filehash": "c0d4e029f2d980ad"
    }
  ],
  "7248e290c5a26934": [
    {
      "graph_id_type": "md_id",
      "proprietary_id": "mp-1226807",
      "datasource": "MP",
      "url": "https://next-gen.materialsproject.org/materials/mp-1226807",
      "filehash": "5cdb0be8bf3230cb"
    }
  ],
  "5a851c5176ed6224": [
    {
      "graph_id_type": "topo_md_id",
      "proprietary_id": "mp-1226807",
      "datasource": "MP",
      "url": "https://next-gen.materialsproject.org/materials/mp-1226807",
      "filehash": "5cdb0be8bf3230cb"
    }
  ],
  "f6ad2eb1f67d21af": [
    {
      "graph_id_type": "dc_id",
      "proprietary_id": "mp-1226807",
      "datasource": "MP",
      "url": "https://next-gen.materialsproject.org/materials/mp-1226807",
      "filehash": "5cdb0be8bf3230cb"
    }
  ]
}