{
  "5f84fde767059081": [
    {
      "graph_id_type": "md_id",
      "proprietary_id": "mp-2819",
      "datasource": "MP",
      "url": "https://next-gen.materialsproject.org/materials/mp-2819",
      "filehash": "00263a6e45870c37"
    }
  ],
  "69bc95bdfa363713": [
    {
      "graph_id_type": "topo_md_id",
      "proprietary_id": "mp-2819",
      "datasource": "MP",
      "url": "https://next-gen.materialsproject.org/materials/mp-2819",
      "filehash": "00263a6e45870c37"
    }
  ],
  "139f2c0207b2b95b": [
    {
      "graph_id_type": "dc_id",
      "proprietary_id": "mp-2819",
      "datasource": "MP",
      "url": "https://next-gen.materialsproject.org/materials/mp-2819",
      "filehash": "00263a6e45870c37"
    }
  ],
  "8134e4ffda10d1f5": [
    {
      "graph_id_type": "md_id",
      "proprietary_id": "mp-2597",
      "datasource": "MP",
      "url": "https://next-gen.materialsproject.org/materials/mp-2597",
      "filehash": "90691eb8faa4860c"
    }
  ],
  "252fa7f858cec6d0": [
    {
      "graph_id_type": "topo_md_id",
      "proprietary_id": "mp-2597",
      "datasource": "MP",
      "url": "https://next-gen.materialsproject.org/materials/mp-2597",
      "filehash": "90691eb8faa4860c"
    }
  ],
  "8b6323bca2433926": [
    {
      "graph_id_type": "dc_id",
      "proprietary_id": "mp-2597",
      "datasource": "MP",
      "url": "https://next-gen.materialsproject.org/materials/mp-2597",
      "filehash": "90691eb8faa4860c"
    }
  ]
}