{
  "7cd298ee526f55cf": [
    {
      "graph_id_type": "md_id",
      "proprietary_id": "mp-569939",
      "datasource": "MP",
      "url": "https://next-gen.materialsproject.org/materials/mp-569939",
      "filehash": "655a847f00515137fb3d26c74c6430cc5e7e056aa89ce12ffa80ba6dd627d5bc"
    }
  ],
  "19ca7c8bb4804d25": [
    {
      "graph_id_type": "topo_md_id",
      "proprietary_id": "mp-569939",
      "datasource": "MP",
      "url": "https://next-gen.materialsproject.org/materials/mp-569939",
      "filehash": "655a847f00515137fb3d26c74c6430cc5e7e056aa89ce12ffa80ba6dd627d5bc"
    }
  ],
  "6613c1c47ba0a8c5": [
    {
      "graph_id_type": "dc_id",
      "proprietary_id": "mp-569939",
      "datasource": "MP",
      "url": "https://next-gen.materialsproject.org/materials/mp-569939",
      "filehash": "655a847f00515137fb3d26c74c6430cc5e7e056aa89ce12ffa80ba6dd627d5bc"
    }
  ]
}