{
  "83c3aa3377b74258": [
    {
      "graph_id_type": "md_id",
      "proprietary_id": "mp-756139",
      "datasource": "MP",
      "url": "https://next-gen.materialsproject.org/materials/mp-756139",
      "filehash": "ee623b1a08724a1f"
    }
  ],
  "8b6eea038cb3f4f6": [
    {
      "graph_id_type": "topo_md_id",
      "proprietary_id": "mp-756139",
      "datasource": "MP",
      "url": "https://next-gen.materialsproject.org/materials/mp-756139",
      "filehash": "ee623b1a08724a1f"
    }
  ],
  "653c262522d71fd8": [
    {
      "graph_id_type": "dc_id",
      "proprietary_id": "mp-756139",
      "datasource": "MP",
      "url": "https://next-gen.materialsproject.org/materials/mp-756139",
      "filehash": "ee623b1a08724a1f"
    }
  ],
  "5ace5ed293013c65": [
    {
      "graph_id_type": "md_id",
      "proprietary_id": "mp-755991",
      "datasource": "MP",
      "url": "https://next-gen.materialsproject.org/materials/mp-755991",
      "filehash": "450f9c5533f60081"
    }
  ],
  "1dbcd2c8033a9238": [
    {
      "graph_id_type": "topo_md_id",
      "proprietary_id": "mp-755991",
      "datasource": "MP",
      "url": "https://next-gen.materialsproject.org/materials/mp-755991",
      "filehash": "450f9c5533f60081"
    }
  ],
  "359f7c0a75cfd1e7": [
    {
      "graph_id_type": "dc_id",
      "proprietary_id": "mp-755991",
      "datasource": "MP",
      "url": "https://next-gen.materialsproject.org/materials/mp-755991",
      "filehash": "450f9c5533f60081"
    }
  ]
}